Workbook
Name Stable_Growth_Rate: 'Valuation- DDM'!$C$16
Name Value_Per_Share: 'Valuation- DDM'!$C$11

Sheet Cover sheet
A2: Company Name | B2: KPR Mills Ltd.
A4: Group Number | B4: 4
A6: Group Members
A7: Sr. no. | B7: Name | C7: SAP ID | D7: Contribution
D8: Phase- 1 | E8: Phase- 2 | F8: Phase- 3
A9: 1 | B9: Ananya Chengta | C9: 74022020084 | D9: Company Analysis | E9: Case, Income Statement & Balance Sheet | F9: Ratios, DDM Valuation, Relative Valuation & Buy/Sell Decision
A10: 2 | B10: Anshula Sonkusale | C10: 74022019935 | D10: Economic Analysis | E10: Income Statement & Balance Sheet | F10: Ratios, FCFF Valuation, Relative Valuation & Buy/Sell Decision
A11: 3 | B11: Bharathi Kyathi Ganapathiraju | C11: 74022019585 | D11: Industry Analysis | E11: Income Statement & Balance Sheet | F11: Ratios, DDM Valuation, Relative Valuation & Buy/Sell Decision
A12: 4 | B12: Devak Patel | C12: 74022019994 | D12: Industry Analysis | E12: Income Statement, Balance Sheet & Cash Flow Statement (Little Corrections) | F12: Ratios, FCFF Valuation, Relative Valuation & Buy/Sell Decision
A13: 5 | B13: Forum Chandarana | C13: 74022020335 | D13: Economic Analysis | E13: Income Statement & Balance Sheet | F13: Ratios, FCFF Valuation, Relative Valuation & Buy/Sell Decision
A14: 6 | B14: Mini Kaintura | C14: 74022020225 | D14: Company Analysis | E14: Case & Cash Flow Statement, Balance Sheet from Liabilities and Income Statement (Little Corrections) | F14: Ratios

Sheet EIC Analysis
B2: KPR MILLS LTD
B3: Sr. No. | C3: Category (E/I/C) | D3: Indicator | E3: Source | F3: Url/Link | G3: Page No. (if applicable) | H3: Information | I3: Which Financial Indicator is affected? | J3: Range of Impact
B4: 1 | C4: E | D4: Union Budget | E4: The Press Information Bureau (PIB) | F4: https://pib.gov.in/PressReleasePage.aspx?PRID=1794167 https://www.pib.gov.in/PressReleasePage.aspx?PRID=1894932#:~:text=Nirmala%20Sitharaman%20tabled%20the%20Economic,ADB%20and%20by%20RBI%2C%20domestically. | G4: - | H4: - Finance Minister Nirmala Sitharaman released budget for 2022- 2023 in which India’s GDP growth for FY 24 is anticipated at 6.5%, - Despite the shocks like Covid – 19, Russia – Ukraine conflict, inflation (appreciation of US dollar), India is projected as the fastest growing economy in the world. Currently India is 5th largest economy in the world. - In the Budget, 7 activities is given the priority, “Saptarishi” that includes -Infrastructure and investment, Inclusive development, Reaching the last mile, unleashing the potential, green growth, financial sector, youth power. - Urban Infrastructure Development Fund (UIDF) is established to create infrastructure in Tier 2 and Tier 3 cities. - Raising capital expenditure by 33% to Rs 10 lakh crore , which is 3.3% of economic output to boost demand and consumption in the economy. | I4: Sales Growth Rate & Capital Investment | J4: Increase
B5: 2 | C5: E | D5: Infrastructure development | E5: TOI, business Standards | F5: https://timesofindia.indiatimes.com/business/budget/infrastructure-development-capex-hiked-by-33-to-rs-10-lakh-crore-for-2023-24-fm/articleshow/97517443.cms https://www.business-standard.com/budget/article/budget-pushes-for-developing-transport-urban-infrastructure-housing-123020100581_1.html | G5: - | H5: - Union budget focuses on infrastructure development by allocating capex of 10 lakh crore. Adding to it, there will be more opportunity for private investment in the new infrastructure finance secretariat. - Railway ministry has been given capex of 2.4 lakh crores in FY 24 for 100 crucial transport infrastructure projects for better last-mile connectivity and connectivity to ports of commodities like coal, fertiliser, food grain sector. - Gati Shakti - National Master Plan, introduced by PM Narendra Modi in October 2022 which aimed at developing an integrated infrastructure to reduce the cost of logistic and improving India’s overall competitiveness. | I5: Cost of transportation and distribution | J5: Decrease
B6: 3 | C6: E | D6: FTA | E6: Financial express, mint, business standards | F6: https://www.financialexpress.com/economy/india-bangladesh-to-start-fta-talks-early/2923881/ , https://www.livemint.com/news/india/india-bangladesh-to-soon-start-talks-for-free-trade-pact-details-here-11671764046997.html , https://www.business-standard.com/article/international/australia-approves-fta-with-india-to-implement-on-mutually-agreed-date-122112200615_1.html , https://www.financialexpress.com/economy/expect-to-sign-at-least-2-more-ftas-in-2023-says-piyush-goyal/2930671/ , https://kprmilllimited.com/file/wp-content/uploads/2022/07/Annual-Report-2022.pdf | G6: 6/188 of annual report | H6: - India and Bangladesh have decided to sign FTA , discussing about feasibility of bilateral trade in rupee, removal of non- tariff barriers and port restrictions, mutual recognition of standards to boost bilateral commerce. The bilateral trade between India and Bangladesh increased $ 18.2 million in 2021-22 as against $10.8 billion in 2020. -India and Australia have entered into Economic Cooperation and Trade Agreement (ECTA), this will give Indian exporters duty-free access to the Australian market for over 6,000 diverse products ( by eliminating custom duty on 98.3% of traded goods and on 100% tariff lines for 5 years), including textiles, leather, furniture, jewellery, and machinery. Bilateral trade is expected to cross $45-50 billion in five years from $25 billion at present after the trade deal comes into force. - Union Commerce Minister Piyush Goyal expects 2 more FTA to be signed in 2023 with UK, European Union and Canada. “India today works from a position of strength, we negotiate with confidence,” Goyal said. | I6: Exports | J6: Increase
B7: 4 | C7: E | D7: Employment | E7: Times of India, Press Information Bureau, OkCredit and IndexMundi | F7: Textile industry supporting Indian employment (indiatimes.com) , India Age structure - Demographics (indexmundi.com), https://okcredit.in/blog/all-about-the-economy-of-india/, https://static.pib.gov.in/WriteReadData/specificdocs/documents/2022/feb/doc202222418201.pdf | G7: 45179 | H7: - India is on its way to surpass China as the most populated nation on earth. Out of this, 41.56% consists of the working population and is increasing over the years. Agri sector has highest employment. Followed by, manufacturing sector and then tertiary economic sector. - Textile being one of India's major industries, this consumer cyclical sector needs skilled and unskilled human resources. It is the 2nd largest employment provider after agricultural sector with prime presence in rural areas which has abundance of unskilled manpower. - The rise of gig economy globally has caused a major shift in the employment trends. These include freelancers, on-call workers, contractual workers, etc. There has been a projected growth of 22.7% in FY-21 in the flexi-staffing industry. This predominantly prevails among blue collar jobs (eg- UrbanClap, Ola & Uber drivers, etc). Blue collar job gigs is also emerging (eg- web designers). | I7: Human Resourace Expenditure | J7: Decrease
B8: 5 | C8: E | D8: Geopolitical- Russia and Ukraine War | E8: Economic Times and Business Toay | F8: https://economictimes.indiatimes.com/news/economy/finance/indias-slowing-economic-recovery-faces-fresh-geopolitical-risks/articleshow/89884800.cms, shorturl.at/cjkwC | G8: - | H8: -Amid the virus outbreak and its various waves, Russia’s invasion on Ukraine, has slowed down the India’s economic growth. In the rise of Russia’s actions, it has created hinderance in the global trading chains. This crisis has increased commodity prices, hurts FIIs and FDIs and nation’s GDP despite rising inflation. Apprehensions about receiving payments for exports to Russia and Ukraine. - The January 2022 Household Inflation Expectations Survey expected inflation to be higher at 9.7% in February, and at 10.6 per cent in the coming three months, and 10.7% for the coming year, 2023, where in comparison RBI’s target is of 4.5% for the year. | I8: Cost of Production | J8: Increase
B9: 6 | C9: E | D9: Inflation | E9: The Financial Express | F9: Economic Survey 2023-24 Live Updates: Union Budget Economic Survey 2023 Live Announcements, 2023 Economic Survey of India Live Updates | The Financial Express, Inflation in India expected to come down to 5 % in 2023 and 4 % in 2024, says IMF | The Financial Express | G9: - | H9: - In reference to the Economic Survey 2023, RBI is capable to tackle inflation and is within its target despite the likelihood of global recession. The global inflation is set to fall (disinflation) from 8.8 percent in 2022 (annual average) to 6.6 percent in 2023 and 4.3 percent in 2024. The nation was successful to recover from the pandemic and after the declaration of the new budget as announced on 1st Feb 2023, GDP is set to increase by 6.5% growth rate in FY2024. Increased demand and capex, economy is set to grow. | I9: Expenditure | J9: Approximately Stable
B10: 7 | C10: I | D10: Demand | E10: IMARC Group | F10: https://www.imarcgroup.com/indian-textiles-apparel-market | G10: - | H10: - Towards the end of 2022, the Indian textile and apparel market is expected to reach US$ 172.2 billion and the sugar market sized reached 189.0 million tons . - Based on IMARC Group's forecast, the market of textiles and apparels will reach US $ 387.3 billion by 2028, exhibiting a growth rate (CAGR) of 14.59% and sugar market is expected to reach 217.2 million tons by 2028, exhibiting a growth rate (CAGR) of 1.64% - 152 billion dollars were spent on domestic textiles and apparel in 2021, and this number is expected to grow to $225 billion dollars by 2025 due to a CAGR of 12%. - Textile industry leaders predicted 2023-2024 budgetary measures would also boost domestic demand for textile products due to tax cuts and other measures. | I10: Sales Growth Rate | J10: Increase
B11: 8 | C11: I | D11: Raw Material | E11: Business Standard , Just Style , CBNC | F11: https://www.business-standard.com/article/companies/raw-material-price-hike-pinch-india-s-textiles-apparel-exports-in-2022-23-122061900443_1.html https://www.just-style.com/news/industry-news/textile-raw-material-prices-continue-to-increase/ https://www.cnbctv18.com/market/commodities/india-may-raise-sugarcane-frp-price-that-mills-have-to-pay-farmers-14351732.htm | G11: - | H11: - Following COVID, there has been a gradual increase in the price of raw materials like cotton, silk, and wool, which is reflected in the price of yarn (a key raw material). In addition, the price of electricity has spiked up as well. -According to Fiore 21.5% of respondents reported paying low prices in July as opposed to 8.3% in June. The ISM Prices Index registered 60% in July, 18.5 percentage points lower compared to the June reading of 78.5%, indicating raw material prices increased for the twenty-sixth consecutive month, albeit at a much slower rate. - In July, 12 of 18 industries reported paying increased prices for raw materials, with textile mills among them. On the other side the price of sugarcane per quintal was also increase, the union cabinet also approved this the highest even fair and remuneration price (FRP) of ₹305 per quintal. | I11: Cost of Sales , Sales and Sales Growth Rate. | J11: Increase- Cost of Sales Decrease- Sales and Sales Growth Rate
B12: 9 | C12: I | D12: Export | E12: Investindia.gov.in , Annual Report | F12: https://www.investindia.gov.in/sector/textiles-apparel | G12: 110 | H12: During FY22, India exported US$ 44.4 billion worth of textiles, apparel and handicrafts, a 41% increase over FY21. 6.99 billion dollars was exported for readymade clothing and cotton accessories in FY22. By 2027, India's readymade garment exports will grow by 12 to 13% and surpass 13,000,000 U.S. dollars. Robust opportunities in US market gives strong visibility for sustained growth in exports (currently Europe is the key market for garment exports) due to increased demand for cotton products. This is backed by strong financials suggesting a growth of revenue in the overseas market from 106,694 lakhs to 152,427 lakhs from the previous to the current financial year. | I12: Revenue | J12: Increase
B13: 10 | C13: I | D13: Exchange Rate | E13: Fiber2Fashion | F13: https://www.fibre2fashion.com/industry-article/9494/exchange-rate-volatility-and-textile-trade | G13: - | H13: International trade is heavily reliant on exchange rate volatility since almost all transactions are done in dollars. Dollar volatility inhibits businesses from making deals with overseas consumers. Textile and apparel producers are having difficulty calculating their production costs due to foreign currency fluctuations. In addition to creating uncertainty about returns, exchange rate volatility also restricts investment. As a result of foreign exchange fluctuations, governments may also have difficulty meeting their export targets. Since 2000 the Doller has appreciated 22 %against the yen and 13% against Euro. | I13: Revenue form Exports | J13: May Decrease
B14: 11 | C14: I | D14: Growth Drivers:- Technology | E14: FibreGuard and Fiber2Fashion | F14: https://fibreguard.com/sell/blog/how-technology-is-changing-the-textile-industry, https://www.fibre2fashion.com/industry-article/543/indian-textile-industry?amp=true | G14: - | H14: The textile industry is rapidly changing due and the advancements in manufacturing Process and design system. The way we see fabrics are now being revolutionise from better quality fabrics to artificial intelligence drive textile. -Digital twin technology which mainly focus on reducing the waste and boosts sustainability is showing a huge impact on the industry. - Under the Technology Upgradation Fund Scheme (TUFS) for benchmarked projects of modernization, the government reimburses 5% interest for loans and/or finance raised from designated financial institutions. | I14: Cost of Capital on new Technology Purchase | J14: Decrease
B15: 12 | C15: I | D15: Production Linked Incentive Scheme (PLI) | E15: Ministry of Textiles , India Briefing | F15: https://pli.texmin.gov.in/Guidelines/Approved%20Guidelines%20for%20PLI%20scheme%20for%20Textiles.pdf https://www.india-briefing.com/news/india-pli-scheme-for-textiles-full-list-of-beneficiaries-24948.html/#:~:text=The%20scheme%20has%20two%20parts,turnover%20required%20INR%202%20billion. https://pib.gov.in/PressReleaseIframePage.aspx?PRID=1816795 | G15: 5 | H15: - The government has started the Production Linked Incentive (PLI) Scheme with the objective to encourage the manufacture of MMF apparel, MMF fabrics, and products of technical textiles in the nation and help the textile industry grow and become competitive with the budget of INR 10,683 crore. - The PLI Scheme has two parts - Minimum investment is ₹ 3 billion and minimum annual turnover required is ₹ 6 billion - Minimum investment is ₹ 1 billion and minimum annual turnover required is ₹ 2 billion. - Total of 64 application are selected, where government has approved 14 projects under part 1 and 50 projects under part 2 in the states of Madhya Pradesh, Gujarat, Andhra Pradesh and Tamil Nadu etc. | I15: Capital Investment and Sales | J15: Incresae
B16: 13 | C16: I | D16: Mega integrated textile region and apparel scheme (PM MITRA) | E16: Ministry of Textiles | F16: https://pib.gov.in/PressReleasePage.aspx?PRID=1765737 | G16: - | H16: - In the union budget 2022-2023 PM MITRA scheme was launched with the objective to achieve the United Nations Sustainable Development Goal 9: “Build resilient infrastructure, promote sustainable industrialization, and foster innovation”. - MITRA park were inspired by 5F vision of the Prime minister – Farm to fibre to factory to fashion to foreign. - It creates an opportunity to create an integrated textile value chain right from spinning, weaving , processing/dyeing, printing and to garment manufacturing at one location which will reduce logistics cost and also improve competitiveness of Indian textile. - It also Intended to generate 1 lakh direct and 2 lakh indirect employment per park . - Ministry of Textiles is planning to set up 7 Mega Integrated Textile Region and Apparel (PM MITRA) Parks with a total outlay of ₹4,445 crore. | I16: Sales Growth Rate | J16: Increase
B17: 14 | C17: C | D17: Energy consumption | E17: Annual Report | F17: https://kprmilllimited.com/file/wp-content/uploads/2022/07/Annual-Report-2022.pdf | G17: Page no 23 (window) and 13 (pdf) | H17: The company has incurred a cost increase by 383%, and an increase in units purchased by 407% from the last year. But due to the increased capacity of production in 2021-22, the company has been able to decrease the per unit electricity consumption in producing yarn, processed fabric, and readymade garment. It decreased from 2.71 units per kg to 2.70 for yarn, 1.15 units per kg to 1.08 for processed fabric and 0.23 units per kg to 0.19 for finished garment from the last year. | I17: Production Cost/Manufacturing Cost | J17: Decrease
B18: 15 | C18: C | D18: Variety of material introduced | E18: Annual Report | F18: https://kprmilllimited.com/file/wp-content/uploads/2022/07/Annual-Report-2022.pdf | G18: Page no 4 (window) | H18: Includes a higher variety within yarn such as compact, melange, colour melange, slub, grindle and vortex. KPR strategically has a vertically integrated alignment from yarn to apparels. This has translated into lower raw material volatility and steady EBITDA margins over the years. Higher proportion of garmenting enhances overall margin profile. | I18: Sales, Demand, Cost of Production | J18: Both Demand and Sales will incraese and Cost of Production will be at stable price
B19: 16 | C19: C | D19: Maximising production capacity | E19: Annual Report | F19: https://kprmilllimited.com/file/wp-content/uploads/2022/07/Annual-Report-2022.pdf | G19: Page no 5 (window) | H19: Increase in the total units produced by establishing a new garment plant that produces 42 million knitted garments per annum in Erode, Tamil Nadu | I19: Sales Growth | J19: Increase
B20: 17 | C20: C | D20: Plant locations | E20: Annual Report, The Textile Magazine | F20: https://www.indiantextilemagazine.in/kpr-mill-an-iconic-success-story/ | G20: Page no 42 (window), 32 (pdf) and page no 176 | H20: KPR has different plant locations within Tamil Nadu, such as Sathyamangalam initially starting with 6000 spindles, to 30420 spindles in 2000, Coimbatore, Tirpur, Perundai, etc, but all the locations are within Tamil Nadu State. Each plant is responsible for different aspects of the production process, for example, spinning, knitting, garmenting, processing and printing etc. In India the sales have grown by 33.02% from the last year. | I20: Cost of Inbound Logistics | J20: Decrease
B21: 18 | C21: C | D21: Subsidiary expansion | E21: Annual Report | F21: https://kprmilllimited.com/file/wp-content/uploads/2022/07/Annual-Report-2022.pdf | G21: Page 176 | H21: Not just focusing on the garment industry, they have successfully managed to expand through their subsidiaries in different industries like sugar, ethanol etc. Out of the 7 subsidiary companies, the company with the highest revenue generation has been KPR Sugar Mills, with 88,652 lakhs, and highest profit after tax at 16,026 lakhs. The other 3 subsidiaries which are Sugar and Apparels Ltd, KPR Exports, PLC, KPR Pte Ltd are all in loss of 794, 829 and 41 lakhs respectively. | I21: Net Profit | J21: Versatile
B22: 19 | C22: C | D22: Gross Margin | E22: ICICI Direct Research PDF | F22: https://www.icicidirect.com/mailimages/IDirect_KPR_Q3FY22.pdf | G22: - | H22: On a QoQ basis, gross margins declined 338 bps to 43.8% as KPR carried low cost cotton inventory in the previous quarter. Yarn spreads continue to remain sturdy as they have moved in tandem with a sharp rise in cotton | I22: Profit Margin | J22: Decrease
B23: 20 | C23: C | D23: Exports | E23: Annual Report | F23: https://kprmilllimited.com/file/wp-content/uploads/2022/07/Annual-Report-2022.pdf | G23: Page 110 | H23: Robust opportunities in US market gives strong visibility for sustained growth in exports (currently Europe is the key market for garment exports) due to increased demand for cotton products. This is backed by strong financials suggesting a growth of revenue in the overseas market from 106,694 lakhs to 152,427 lakhs from the previous to the current financial year. In Ethiopia KPR Mills had to close it's operations due to the unstable political situation over there. | I23: Revenue | J23: Increase
B24: 21 | C24: C | D24: Exchange rate | E24: Annual Report | F24: https://kprmilllimited.com/file/wp-content/uploads/2022/07/Annual-Report-2022.pdf | G24: Page 101 | H24: As the company deals it's international transactions in USD and Euro, the trade recievables are highest at 1620 for Euro and 1155 for USD , when not protected by a forward contract | I24: Revenue | J24: Decrease

Sheet Case
A3: Particulars | B3: 2018 | C3: 2019 | D3: 2020 | E3: 2021 | F3: 2022
A4: Profit and Loss Statement of KPR Mills
A5: I) Revenue from Operations:
A6: (i)Sale of Products
A7: (a) Garment | B7: 59729 | C7: 110164 | D7: 124982 | E7: 121693 | F7: 166911
A8: (b) Yarn | B8: 132632 | C8: 145198 | D8: 126731 | E8: 122320 | F8: 181859
A9: (c) Fabric | B9: 34746 | C9: 16653 | D9: 15647 | E9: 29597 | F9: 27895
A10: (d) Cotton Waste | B10: 9067 | C10: 9930 | D10: 9752 | E10: 8432 | F10: 11408
A11: (e) Accessories and Others | B11: 1397 | C11: 2609 | D11: 1696 | E11: 1752 | F11: 2144
A12: Total of Sale of Products (Gross) | B12: =SUM(B7:B11) -> 237571 | C12: =SUM(C7:C11) -> 284554 | D12: =SUM(D7:D11) -> 278808 | E12: =SUM(E7:E11) -> 283794 | F12: =SUM(F7:F11) -> 390217
A13: Less: Discount allowed | B13: 71 | C13: 763 | D13: 1556 | E13: 395 | F13: 722
A14: Total of Sale of Products (Net) | B14: =B12-B13 -> 237500 | C14: =C12-C13 -> 283791 | D14: =D12-D13 -> 277252 | E14: =E12-E13 -> 283399 | F14: =F12-F13 -> 389495
A15: (ii) Sale of Services
A16: Processing and fabrication income | B16: 7126 | C16: 4534 | D16: 2948 | E16: 4723 | F16: 5374
A17: (iii) Other Operating Revenues | B17: 6526 | C17: 9528 | D17: 9607 | E17: 7242 | F17: 12498
A18: Total Revenue from Operations (i+ii+iii) | B18: =B14+B16+B17 -> 251152 | C18: =C14+C16+C17 -> 297853 | D18: =D14+D16+D17 -> 289807 | E18: =E14+E16+E17 -> 295364 | F18: =F14+F16+F17 -> 407367
A19: II) Other Income
A20: (i) Dividend income from long term investments in subsidiaries | B20: 26 | C20: 26 | D20: 26 | E20: 26 | F20: 26
A21: (ii) Gain on sale of investment (net) | B21: 116 | C21: 181 | D21: 546 | E21: 359 | F21: 1359
A22: (iii) Net gain on sale of property, plant and equipment | B22: 30 | C22: 175 | D22: 215 | E22: 44 | F22: 296
A23: (iv) Rental income | B23: 227 | C23: 3049 | D23: 2582 | E23: 2826 | F23: 2947
A24: (v) Misc Other Income | B24: 1199 | C24: 306 | D24: 277 | E24: 541 | F24: 3835
A25: Total of Other Income | B25: =SUM(B20:B24) -> 1598 | C25: =SUM(C20:C24) -> 3737 | D25: =SUM(D20:D24) -> 3646 | E25: =SUM(E20:E24) -> 3796 | F25: =SUM(F20:F24) -> 8463
A26: III) Total income (I+II) | B26: =B18+B25 -> 252750 | C26: =C18+C25 -> 301590 | D26: =D18+D25 -> 293453 | E26: =E18+E25 -> 299160 | F26: =F18+F25 -> 415830
A27: IV) Expenses:
A28: a) Cost Of Materials Consumed | B28: 164709 | C28: 179914 | D28: 169522 | E28: 137852 | F28: 227875
A29: b) Purchase of stock in trade | B29: 0 | C29: 0 | D29: 19718 | E29: 0 | F29: 0
A30: c) Changes in inventories of finished goods, stock in trade and work in progress | B30: -4513 | C30: -5028 | D30: -18370 | E30: 20087 | F30: -8323
A31: d) Employee benefits expense | B31: 23305 | C31: 37341 | D31: 38325 | E31: 38479 | F31: 43289
A32: e) Finance costs | B32: 3049 | C32: 3586 | D32: 3541 | E32: 1961 | F32: 1339
A33: f) Depreciation and Amortisation Expense | B33: 10497 | C33: 9583 | D33: 9891 | E33: 9792 | F33: 7565
A34: g) Other expenses | B34: 24747 | C34: 34919 | D34: 33159 | E34: 32507 | F34: 46136
A35: V) Total expenses | B35: =B28+SUM(B29:B34) -> 221794 | C35: =C28+SUM(C29:C34) -> 260315 | D35: =D28+SUM(D29:D34) -> 255786 | E35: =E28+SUM(E29:E34) -> 240678 | F35: =F28+SUM(F29:F34) -> 317881
A36: VI) Profit before tax (III-V) | B36: =B26-B35 -> 30956 | C36: =C26-C35 -> 41275 | D36: =D26-D35 -> 37667 | E36: =E26-E35 -> 58482 | F36: =F26-F35 -> 97949
A37: VII) Tax expense
A38: (i) Current tax | B38: 8263 | C38: 12453 | D38: 9140 | E38: 15654 | F38: 24795
A39: (ii) Deffered tax | B39: 196 | C39: -89 | D39: -934 | E39: -434 | F39: 74
A40: Income tax expense | B40: =B38+B39 -> 8459 | C40: =C38+C39 -> 12364 | D40: =D38+D39 -> 8206 | E40: =E38+E39 -> 15220 | F40: =F38+F39 -> 24869
A41: VIII) Profit after tax (VI-VII) | B41: =B36-B40 -> 22497 | C41: =C36-C40 -> 28911 | D41: =D36-D40 -> 29461 | E41: =E36-E40 -> 43262 | F41: =F36-F40 -> 73080
A45: Balance Sheet of KPR Mills
A46: Particulars | B46: 2018 | C46: 2019 | D46: 2020 | E46: 2021 | F46: 2022
A47: Assets
A48: 1) Non current assets
A49: a) Property, plant and equipment | B49: 86436 | C49: 79383 | D49: 86551 | E49: 79680 | F49: 84433
A50: b) Capital work in progress | B50: 10 | C50: 441 | D50: 579 | E50: 1742 | F50: 491
A51: c) Intangible assets | B51: 18 | C51: 20 | D51: 105 | E51: 95 | F51: 80
A52: d) Financial assets
A53: i) Investments | B53: 7851 | C53: 7987 | D53: 8296 | E53: 18714 | F53: 57912
A54: ii) Loans | B54: 826 | C54: 1802 | D54: 352 | E54: 555 | F54: 204
A55: iii) Other financial assets | B55: 0 | C55: 0 | D55: 1177 | E55: 1875 | F55: 2350
A56: e) Other non current assets | B56: 6460 | C56: 5077 | D56: 2756 | E56: 2082 | F56: 3479
A57: Total non current assets | B57: =SUM(B49:B56) -> 101601 | C57: =SUM(C49:C56) -> 94710 | D57: =SUM(D49:D56) -> 99816 | E57: =SUM(E49:E56) -> 104743 | F57: =SUM(F49:F56) -> 148949
A58: 2) Current Assets
A59: a) Inventories | B59: 39134 | C59: 72934 | D59: 49437 | E59: 69085 | F59: 85190
A60: b) Financial assets
A61: (i) Investment | B61: 1202 | C61: 0 | D61: 701 | E61: 23344 | F61: 27403
A62: (ii) Trade receivables | B62: 32419 | C62: 46830 | D62: 35127 | E62: 26081 | F62: 39263 | J62: Other data- Notes to Account
A63: (iii) Cash and cash equivalents | B63: 1641 | C63: 5633 | D63: 14533 | E63: 4503 | F63: 9561 | J63: Particulars | K63: 2018 | L63: 2019 | M63: 2020 | N63: 2021 | O63: 2022
A64: (iv) Other bank balances | B64: 1100 | C64: 1044 | D64: 171 | E64: 787 | F64: 479 | J64: Opening Inventory | K64: 18579 | L64: 21959 | M64: 50060 | N64: 9486 | O64: 47960
A65: (v) Other financial assets | B65: 4196 | C65: 1221 | D65: 249 | E65: 4359 | F65: 4442 | J65: Add: Purchase | K65: 168089 | L65: 208015 | M65: 128948 | N65: 176326 | O65: 234727
A66: (c) Other current assets | B66: 11744 | C66: 17349 | D66: 18686 | E66: 15641 | F66: 20603 | J66: Less: Closing Inventory | K66: 21959 | L66: 50060 | M66: 9486 | N66: 47960 | O66: 54812
A67: Total current assets | B67: =SUM(B59:B66) -> 91436 | C67: =SUM(C59:C66) -> 145011 | D67: =SUM(D59:D66) -> 118904 | E67: =SUM(E59:E66) -> 143800 | F67: =SUM(F59:F66) -> 186941 | J67: Total COGS | K67: =K64+K65-K66 -> 164709 | L67: =L64+L65-L66 -> 179914 | M67: =M64+M65-M66 -> 169522 | N67: =N64+N65-N66 -> 137852 | O67: =O64+O65-O66 -> 227875
A68: Total Assets | B68: 193037 | C68: 239721 | D68: 218720 | E68: =E57+E67 -> 248543 | F68: 335890
A70: Equity and Liabilities
A71: 1) Equity
A72: a) Equity share capital | B72: 3695 | C72: 3628 | D72: 3441 | E72: 3441 | F72: 3441
A73: b) Other equity | B73: 129977 | C73: 147492 | D73: 147047 | E73: 187213 | F73: 259777
A74: Total Equity | B74: =SUM(B72,B73) -> 133672 | C74: =SUM(C72,C73) -> 151120 | D74: =SUM(D72,D73) -> 150488 | E74: =SUM(E72,E73) -> 190654 | F74: =SUM(F72,F73) -> 263218
A75: Liabilities
A76: 2) Non current liabilities
A77: a) Financial liabilities
A78: i) Borrowings | B78: 10126 | C78: 8195 | D78: 6659 | E78: 990 | F78: 31
A79: b) Deffered tax liabilities (net) | B79: 5750 | C79: 5661 | D79: 4727 | E79: 4294 | F79: 4368
A80: c) Other non current liabilities | B80: 0 | C80: 0 | D80: 7 | E80: 4 | F80: 3
A81: Total non current liabilities | B81: =SUM(B78:B80) -> 15876 | C81: =SUM(C78:C80) -> 13856 | D81: =SUM(D78:D80) -> 11393 | E81: =SUM(E78:E80) -> 5288 | F81: =SUM(F78:F80) -> 4402
A82: 3) Current liabilities
A83: a) Financial liabilities
A84: i) Borrowings | B84: 22822 | C84: 55241 | D84: 39876 | E84: 30579 | F84: 41754
A85: ii) Trade payables | B85: 13749 | C85: 12350 | D85: 10574 | E85: =881+9534 -> 10415 | F85: 12406
A86: iii) Other financial liabilities | B86: 3150 | C86: 3192 | D86: 3592 | E86: 5020 | F86: 43
A87: b) Other current liabilities | B87: 3762 | C87: 2915 | D87: 2481 | E87: 4265 | F87: 12395
A88: c) Current tax liabilities (net) | B88: 6 | C88: 1047 | D88: 316 | E88: 2322 | F88: 1672
A89: Total Current Liabilities | B89: =SUM(B84:B88) -> 43489 | C89: =SUM(C84:C88) -> 74745 | D89: =SUM(D84:D88) -> 56839 | E89: =SUM(E84:E88) -> 52601 | F89: =SUM(F84:F88) -> 68270
A90: Total Liabilities | B90: =SUM(B81,B89) -> 59365 | C90: =SUM(C81,C89) -> 88601 | D90: =SUM(D81,D89) -> 68232 | E90: =SUM(E81,E89) -> 57889 | F90: =SUM(F81,F89) -> 72672
A91: Total Equity and Liabilities | B91: =SUM(B90,B74) -> 193037 | C91: =SUM(C90,C74) -> 239721 | D91: =SUM(D90,D74) -> 218720 | E91: =SUM(E90,E74) -> 248543 | F91: =SUM(F90,F74) -> 335890

Sheet Assumptions 
A2: Sr No | B2: Particulars | C2: Figure taken for assumption
A3: Income Statement
A4: 1 | B4: Export Garment Sales is set to increase by 12.5% according to our EIC anaylsis - Point 9 , Exports | C4: 0.125
A5: 2 | B5: Growth % of Yarn is 3.7% due to global urbanisation and advances in upstream textile industry equipement taken from recent news | C5: 0.037 | E5: https://pmarketresearch.com/yarn-market-research-2021/
A6: 3 | B6: Discount allowed is assumed as percent of total sales of the product
A7: 4 | B7: Under the production incentive linkage scheme, it was found that incentives could go upto 10%, therefore the growth in the service would be by 5%. | C7: 0.05
A8: 5 | B8: There is no gain on sales of investment and PPE
A9: 6 | B9: Rental income is assumed as percentage of PPE
A10: 7 | B10: Misc income is assumed to constant of previous years
A11: 8 | B11: For COGS, according to EIC analysis, it is assumed that cotton exports will grow in the range of 12% starting in the year 2022 and grow till 13% in the year 2027. GDP and Inflation taken w.r.t. latest information available on websites. | E11: https://www.statista.com/statistics/271322/inflation-rate-in-india/ | I11: https://www.statista.com/statistics/263617/gross-domestic-product-gdp-growth-rate-in-india/
B12: For CAGR, 14.59% is mentioned in EIC Analysis point- 7 which is assumed to be constant.
A13: 9 | B13: There is no purchase of stock in trade for the foreseeing future | E13: Export Growth -
A14: 10 | B14: Changes in inventories are assumed as proportion of revenue from operation | E14: By 2027, India's readymade garment exports will grow by 12 to 13% and surpass 13,000,000 U.S. dollars.
A15: 11 | B15: Employees benefit is assumed as average % of COGS | E15: Robust opportunities in US market gives strong visibility for sustained growth in exports (currently Europe is the key market for garment exports) due to increased demand for cotton products.
A16: 12 | B16: Finance Cost is increasing with respect to inflation as a proportion of non current borrowings | C16: Interest Rate on Loan: Best case: 4.2%, Base case: 6.2%, Worst case : 8.2% | E16: So Export Garment Sales is set to increase by 12.5%
A17: 13 | B17: Other expenses taken as % of COGS
A18: 14 | B18: Current tax taken as % of pre- tax income. And deferred tax remains unchanged | E18: Inflation Rate-
E19: Inflation Rate Leads to Increase in Cost of Goods sold of KPR mills due to Increase in Prices Of Raw Materials such as Cotton and So on. As Incrase in Cotton Prices mostley follows trend so Inflation till 2027 will be Calculated from the Inflation Rate in India from 1987 to 2022. The Inflation Rate will be 6.6%,4.36%,4.13%,3.99%,4% in Year 2023,2024,2025,2026,2027.
A21: Balance Sheet
A22: 1 | B22: Capex is to be forecasted on the basis of average of historical % of sales
A23: 2 | E23: Under the production incentive linkage scheme, it was found that incentives could go upto 5-10%, therefore the Revenue growth in the Textile service(Labour Work of Fabrication) would be by 5%. As Textile services Require Equipments and New Tecnology to boost Production and Equpments and Technology may funded under PLI "scheme" If KPr millss listed in Scheme 3 List.
A24: 3 | B24: Capital work in progress is taken as % of capex
A25: 4 | B25: Intangible asset is assumed to be constant
A26: 5 | B26: Non current investment and current investment was projected using forecast linear to avoid inconsistency in growth
A27: 6 | B27: Loan is taken as averege proportion of total non current assets
A28: 7 | B28: Other financial assets are assumed to be constant
A29: 8 | B29: Other non current asset & current assets are forecasted as % of sales
A30: 9 | B30: Other bank balances and other financial assets are assumed to constant
A31: 10 | B31: The company had announced a buyback in March 2023 to be closed in April 2024
B32: In 2024, 22.36 lakh shares will be bought back as announced by the company
A33: 11 | B33: Borrowing of non current liability is assumed as % of PPE
A34: 12 | B34: Deferred tax and current tax liability assumed to constant
A35: 13 | B35: Other finanicial liablities is under current liablities is assumed using forecast linear
A36: 14 | B36: Other non current liability taken as % of COGS
A37: 15 | B37: Borrowings in current liabilities is forecasted as the average proportion of Total Current Liabilities from the historical data
A40: Valuation
A41: 1 | B41: In the Indian textile industry, cotton to be precise, in regards of our company, industry is already in the maturing stage of its life cycle. Additionally, as mentioned in our EIC analysis, according to FTA policy, growth is expected.
B42: Hence, Stable Growth Rate is considered as 14% | C42: 0.14
A43: 2 | B43: Dividend is calculated on the basis of Dividend Payout Ratio mentioned in the Annual Report, which is an average of 20-25%
A44: 3 | B44: In DDM, the optimistic scenario is assumed to be 17% stable growth rate, and the pessimistic scenario is assumed to be 10% for scenario analysis

Sheet Input
A3: Particulars | B3: 2018 | C3: 2019 | D3: 2020 | E3: 2021 | F3: 2022 | G3: Forecasting Factor | I3: 2023 | J3: 2024 | K3: 2025 | L3: 2026 | M3: 2027
A4: Income Statement
A5: 1. Revenue Schedule | P5: Case - | Q5: Best Case
A6: Revenue from sales of product: | P6: Particulars | Q6: Interest Rate on Loan
A7: Garments | B7: =Case!B7 -> 59729 | C7: =Case!C7 -> 110164 | D7: =Case!D7 -> 124982 | E7: =Case!E7 -> 121693 | F7: =Case!F7 -> 166911 | I7: =I8+I10 -> 203862.96 | J7: =J8+J10 -> 249892.97 | K7: =K8+K10 -> 307371.68 | L7: =L8+L10 -> 379308.61 | M7: =M8+M10 -> 469526.97 | P7: Worst Case | Q7: 0.1045
A8: Domestic Garments Sales | B8: =B7*(1-B59) -> 41472.367 | C8: =C7*(1-C59) -> 63980.157 | D8: =D7*(1-D59) -> 74620.881 | E8: =E7*(1-E59) -> 78291.767 | F8: =F7*(1-F59) -> 105727.96 | I8: =F8*(1+$G$9) -> 135032.04 | J8: =I8*(1+$G$9) -> 172458.19 | K8: =J8*(1+$G$9) -> 220257.55 | L8: =K8*(1+$G$9) -> 281305.21 | M8: =L8*(1+$G$9) -> 359273.15 | P8: Base Case | Q8: 0.096
A9: Domestic Garments Sales Growth | C9: =(C8/B8)-1 -> 0.54271773 | D9: =(D8/C8)-1 -> 0.16631288 | E9: =(E8/D8)-1 -> 0.04919382 | F9: =(F8/E8)-1 -> 0.35043525 | G9: =AVERAGE(C9:F9) -> 0.27716492 | P9: Best Case | Q9: 0.0875
A10: Export Garment Sales | B10: =B7*B59 -> 18256.633 | C10: =C7*C59 -> 46183.843 | D10: =D7*D59 -> 50361.119 | E10: =E7*E59 -> 43401.233 | F10: =F7*F59 -> 61183.039 | G10: =12.5% -> 0.125 | I10: =F10*(1+$G$10) -> 68830.919 | J10: =I10*(1+$G$10) -> 77434.783 | K10: =J10*(1+$G$10) -> 87114.131 | L10: =K10*(1+$G$10) -> 98003.398 | M10: =L10*(1+$G$10) -> 110253.82
A11: Yarn | B11: =Case!B8 -> 132632 | C11: =Case!C8 -> 145198 | D11: =Case!D8 -> 126731 | E11: =Case!E8 -> 122320 | F11: =Case!F8 -> 181859 | G11: 0.037 | I11: =F11*(1+$G$11) -> 188587.78 | J11: =I11*(1+$G$11) -> 195565.53 | K11: =J11*(1+$G$11) -> 202801.46 | L11: =K11*(1+$G$11) -> 210305.11 | M11: =L11*(1+$G$11) -> 218086.4
A12: Fabric | B12: =Case!B9 -> 34746 | C12: =Case!C9 -> 16653 | D12: =Case!D9 -> 15647 | E12: =Case!E9 -> 29597 | F12: =Case!F9 -> 27895 | G12: =AVERAGE(C13:F13) -> 0.063226883 | I12: =F12*(1+$G$12) -> 29658.714 | J12: =I12*(1+$G$12) -> 31533.942 | K12: =J12*(1+$G$12) -> 33527.735 | L12: =K12*(1+$G$12) -> 35647.589 | M12: =L12*(1+$G$12) -> 37901.475
A13: Fabric Growth | C13: =C12/B12-1 -> -0.52072181 | D13: =D12/C12-1 -> -0.060409536 | E13: =E12/D12-1 -> 0.89154471 | F13: =F12/E12-1 -> -0.057505828
A14: Cotton waste | B14: =Case!B10 -> 9067 | C14: =Case!C10 -> 9930 | D14: =Case!D10 -> 9752 | E14: =Case!E10 -> 8432 | F14: =Case!F10 -> 11408 | G14: =AVERAGE(C15:F15) -> 0.073709793 | I14: =F14*(1+$G$14) -> 12248.881 | J14: =I14*(1+$G$14) -> 13151.744 | K14: =J14*(1+$G$14) -> 14121.156 | L14: =K14*(1+$G$14) -> 15162.024 | M14: =L14*(1+$G$14) -> 16279.613
A15: Cotton Waste Growth | C15: =(C14/B14)-1 -> 0.095180324 | D15: =(D14/C14)-1 -> -0.017925478 | E15: =(E14/D14)-1 -> -0.13535685 | F15: =(F14/E14)-1 -> 0.35294118
A16: Accessories and others | B16: =Case!B11 -> 1397 | C16: =Case!C11 -> 2609 | D16: =Case!D11 -> 1696 | E16: =Case!E11 -> 1752 | F16: =Case!F11 -> 2144 | G16: =AVERAGE(C17:F17) -> -0.031059782 | I16: =F16*(1+$G$16) -> 2077.4078 | J16: =I16*(1+$G$16) -> 2012.884 | K16: =J16*(1+$G$16) -> 1950.3643 | L16: =K16*(1+$G$16) -> 1889.7864 | M16: =L16*(1+$G$16) -> 1831.09
A17: Accessories and others Growth | D17: =D16/C16-1 -> -0.34994251 | E17: =E16/D16-1 -> 0.033018868 | F17: =F16/E16-1 -> 0.22374429
A18: Less: Discount allowed | B18: =Case!B13 -> 71 | C18: =Case!C13 -> 763 | D18: =Case!D13 -> 1556 | E18: =Case!E13 -> 395 | F18: =Case!F13 -> 722 | G18: =AVERAGE(B19:F19) -> 0.0023694491 | I18: =$G$18*I20 -> 1031.6678 | J18: =$G$18*J20 -> 1163.3845 | K18: =$G$18*K20 -> 1323.2169 | L18: =$G$18*L20 -> 1518.3306 | M18: =$G$18*M20 -> 1757.8178
A19: Average Discount | B19: =B18/B20 -> 0.00029894737 | C19: =C18/C20 -> 0.0026885983 | D19: =D18/D20 -> 0.0056122228 | E19: =E18/E20 -> 0.0013937946 | F19: =F18/F20 -> 0.0018536823
A20: Total Sales From Product | B20: =B7+B11+B12+B14+B16-B18 -> 237500 | C20: =C7+C11+C12+C14+C16-C18 -> 283791 | D20: =D7+D11+D12+D14+D16-D18 -> 277252 | E20: =E7+E11+E12+E14+E16-E18 -> 283399 | F20: =F7+F11+F12+F14+F16-F18 -> 389495 | I20: =I7+I11+I12+I14+I16-I18 -> 435404.08 | J20: =J7+J11+J12+J14+J16-J18 -> 490993.69 | K20: =K7+K11+K12+K14+K16-K18 -> 558449.17 | L20: =L7+L11+L12+L14+L16-L18 -> 640794.79 | M20: =M7+M11+M12+M14+M16-M18 -> 741867.73
A21: Revenue from sales from service:
A22: Processing and fabrication income | B22: =Case!B16 -> 7126 | C22: =Case!C16 -> 4534 | D22: =Case!D16 -> 2948 | E22: =Case!E16 -> 4723 | F22: =Case!F16 -> 5374 | G22: 0.05 | I22: =F22*(1+$G$22) -> 5642.7 | J22: =I22*(1+$G$22) -> 5924.835 | K22: =J22*(1+$G$22) -> 6221.0768 | L22: =K22*(1+$G$22) -> 6532.1306 | M22: =L22*(1+$G$22) -> 6858.7371
A24: Other Operating Revenues (growth rate) | C24: =Case!C17/Case!B17-1 -> 0.46000613 | D24: =Case!D17/Case!C17-1 -> 0.0082913518 | E24: =Case!E17/Case!D17-1 -> -0.24617466 | F24: =Case!F17/Case!E17-1 -> 0.72576636 | G24: =AVERAGE(C24:F24) -> 0.23697229
A26: Other income:
A27: (i) Dividend income from long term investments in subsidiaries | G27: =Case!F20 -> 26
A28: (ii) Gain on sale of investment (net) | G28: 0
A29: (iii) Net gain on sale of property, plant and equipment | G29: 0
A30: (iv) Rental income Ratio | B30: =Case!B23/Case!B49 -> 0.0026262206 | C30: =Case!C23/Case!C49 -> 0.038408727 | D30: =Case!D23/Case!D49 -> 0.029832122 | E30: =Case!E23/Case!E49 -> 0.035466867 | F30: =Case!F23/Case!F49 -> 0.034903415 | G30: =AVERAGE(B30:F30) -> 0.02824747 | P30: 0.066 | Q30: 0.0436 | R30: 0.0413 | S30: 0.0399 | T30: 0.04
A31: (v) Misc Other Income | G31: =Case!F24 -> 3835
A33: 2. Cost of Materials Consumed Schedule | B33: =Case!B28 -> 164709 | C33: =Case!C28 -> 179914 | D33: =Case!D28 -> 169522 | E33: =Case!E28 -> 137852 | F33: =Case!F28 -> 227875 | I33: ='Model- Income statement'!G17*Input!I41 -> 139559.08 | J33: ='Model- Income statement'!H17*Input!J41 -> 27230.715 | K33: ='Model- Income statement'!I17*Input!K41 -> 125750.03 | L33: ='Model- Income statement'!J17*Input!L41 -> 137095.9 | M33: ='Model- Income statement'!K17*Input!M41 -> 175254.05
O34: Inflation | P34: % | R34: GDP | S34: %
A35: Growth (% of revenue) | B35: =B33/Case!B18 -> 0.65581401 | C35: =C33/Case!C18 -> 0.60403622 | D35: =D33/Case!D18 -> 0.58494791 | E35: =E33/Case!E18 -> 0.46671903 | F35: =F33/Case!F18 -> 0.55938503 | O35: 2022 | P35: 0.0572 | R35: 2022 | S35: 0.0684
A36: Add: Inflation | I36: =$P36/$P35-1 -> 0.15384615 | J36: =Input!P37/Input!P36-1 -> -0.33939394 | K36: =Input!P38/Input!P37-1 -> -0.052752294 | L36: =(Input!P39/Input!P38)-1 -> -0.033898305 | M36: =(Input!P40/Input!P39)-1 -> 0.0025062657 | O36: 2023 | P36: 0.066 | R36: 2023 | S36: 0.0606
A37: Add: CAGR | I37: 0.1459 | J37: =I37 -> 0.1459 | K37: =J37 -> 0.1459 | L37: =K37 -> 0.1459 | M37: =L37 -> 0.1459 | O37: 2024 | P37: 0.0436 | R37: 2024 | S37: 0.0681
A38: Add: GDP | I38: =(Input!S36/Input!S35)-1 -> -0.11403509 | J38: =(Input!S37/Input!S36)-1 -> 0.12376238 | K38: =(Input!S38/Input!S37)-1 -> -0.0044052863 | L38: =(Input!S39/Input!S38)-1 -> -0.036873156 | M38: =(Input!S40/Input!S39)-1 -> -0.055130168 | O38: 2025 | P38: 0.0413 | R38: 2025 | S38: 0.0678
A39: Add: Exports | I39: 0.12 | J39: =I39+$G$40 -> 0.1225 | K39: =J39+$G$40 -> 0.125 | L39: =K39+$G$40 -> 0.1275 | M39: 0.13 | O39: 2026 | P39: 0.0399 | R39: 2026 | S39: 0.0653
A40: Export Growth Factor | G40: =(M39-I39)/4 -> 0.0025 | O40: 2027 | P40: 0.04 | R40: 2027 | S40: 0.0617
A41: Adjusted Growth Rate | I41: =SUM(I36:I40) -> 0.30571107 | J41: =SUM(J36:J40) -> 0.052768437 | K41: =SUM(K36:K40) -> 0.21374242 | L41: =SUM(L36:L40) -> 0.20262854 | M41: =SUM(M36:M40) -> 0.2232761
A43: Dep Growth Rate | C43: =(Case!C33/Case!B33)-1 -> -0.087072497 | D43: =(Case!D33/Case!C33)-1 -> 0.032140248 | E43: =(Case!E33/Case!D33)-1 -> -0.010009099 | F43: =(Case!F33/Case!E33)-1 -> -0.22743056 | G43: =AVERAGE(C43:F43) -> -0.073092976
A45: Changes in inventories of finished goods, stock in trade and work in progress (% of revenue) | C45: =Case!C30/Case!C18 -> -0.01688081 | D45: =Case!D30/Case!D18 -> -0.063387013 | E45: =Case!E30/Case!E18 -> 0.068007611 | F45: =Case!F30/Case!F18 -> -0.020431208 | G45: =AVERAGE(B45:F45) -> -0.0081728551
A47: Employee benefits expense (% of COGS) | B47: =Case!B31/Case!B28 -> 0.14149196 | C47: =Case!C31/Case!C28 -> 0.20754916 | D47: =Case!D31/Case!D28 -> 0.22607685 | E47: =Case!E31/Case!E28 -> 0.27913269 | F47: =Case!F31/Case!F28 -> 0.18996818 | G47: =AVERAGE(B47:F47) -> 0.20884377
A49: Finance costs | G49: =VLOOKUP(Q5,P6:Q9,2,FALSE) -> 0.0875
A51: Other expenses | B51: =Case!B34/Case!B28 -> 0.1502468 | C51: =Case!C34/Case!C28 -> 0.19408717 | D51: =Case!D34/Case!D28 -> 0.19560293 | E51: =Case!E34/Case!E28 -> 0.23581087 | F51: =Case!F34/Case!F28 -> 0.20246188 | G51: =AVERAGE(B51:F51) -> 0.19564193
A53: VII) Tax expense
A54: (i) Current tax | C54: =Case!C38/Case!C36 -> 0.30170806 | D54: =Case!D38/Case!D36 -> 0.24265272 | E54: =Case!E38/Case!E36 -> 0.2676721 | F54: =Case!F38/Case!F36 -> 0.25314194 | G54: =AVERAGE(B54:F54) -> 0.26629371
A55: (ii) Deffered tax | G55: =Case!F39 -> 74
A57: Export Sales | B57: 77255 | C57: 126435 | D57: 118246 | E57: =106694 -> 106694 | F57: 152427
A58: Total Revenue | B58: 252750 | C58: 301590 | D58: 293453 | E58: 299160 | F58: 415830
A59: Export Sales/Revenue | B59: =B57/B58 -> 0.30565776 | C59: =C57/C58 -> 0.41922809 | D59: =D57/D58 -> 0.40294698 | E59: =E57/E58 -> 0.35664527 | F59: =F57/F58 -> 0.36656085 | G59: =AVERAGE(B59:F59) -> 0.37020779
A62: BALANCE SHEET
A64: 1. PPE Schedule
A65: Opening PPE | B65: =B70-B68+B69 -> 93994 | C65: =C70-C68+C69 -> 72645 | D65: =D70-D68+D69 -> 93588 | E65: =E70-E68+E69 -> 75224 | F65: =F70-F68+F69 -> 78446 | I65: =F70 -> 84433 | J65: =I70 -> 88474.85 | K65: =J70 -> 93716.69 | L65: =K70 -> 100383.17 | M65: =L70 -> 108763.56
A66: Addition to Capex (Purchase) | B66: 3032 | C66: 16840 | D66: 3542 | E66: 12561 | F66: 14082
A67: Disposals to Capex (Sales) | B67: 831 | C67: 229 | D67: 815 | E67: 565 | F67: 530
A68: (+) Capex | B68: =B66-B67 -> 2201 | C68: =C66-C67 -> 16611 | D68: =D66-D67 -> 2727 | E68: =E66-E67 -> 11996 | F68: =F66-F67 -> 13552 | I68: ='Model- Income statement'!G17*$G$71 -> 13496.526 | J68: ='Model- Income statement'!H17*$G$71 -> 15256.674 | K68: ='Model- Income statement'!I17*$G$71 -> 17393.719 | L68: ='Model- Income statement'!J17*$G$71 -> 20003.175 | M68: ='Model- Income statement'!K17*$G$71 -> 23206.033
A69: (-) Dep | B69: 9759 | C69: 9873 | D69: 9764 | E69: 7540 | F69: 7565 | I69: =I70*$G$72 -> 9454.6763 | J69: =J70*$G$72 -> 10014.834 | K69: =K70*$G$72 -> 10727.234 | L69: =L70*$G$72 -> 11622.786 | M69: =M70*$G$72 -> 12741.099
A70: Closing PPE | B70: =Case!B49 -> 86436 | C70: =Case!C49 -> 79383 | D70: =Case!D49 -> 86551 | E70: =Case!E49 -> 79680 | F70: =Case!F49 -> 84433 | I70: =I65+I68-I69 -> 88474.85 | J70: =J65+J68-J69 -> 93716.69 | K70: =K65+K68-K69 -> 100383.17 | L70: =L65+L68-L69 -> 108763.56 | M70: =M65+M68-M69 -> 119228.5
A71: Capex Growth Rate | B71: =B68/Case!B18 -> 0.0087636173 | C71: =C68/Case!C18 -> 0.055769121 | D71: =D68/Case!D18 -> 0.0094097106 | E71: =E68/Case!E18 -> 0.040614293 | F71: =F68/Case!F18 -> 0.0332673 | G71: =AVERAGE(B71:F71) -> 0.029564808
A72: Deperication Rate | B72: =B69/B70 -> 0.11290435 | C72: =C69/C70 -> 0.12437172 | D72: =D69/D70 -> 0.1128121 | E72: =E69/E70 -> 0.094628514 | F72: =F69/F70 -> 0.089597669 | G72: =AVERAGE(B72:F72) -> 0.10686287
A74: Capital work in progress (% of capex) | B74: =Case!B50/Input!B68 -> 0.0045433894 | C74: =Case!C50/Input!C68 -> 0.026548673 | D74: =Case!D50/Input!D68 -> 0.21232123 | E74: =Case!E50/Input!E68 -> 0.14521507 | F74: =Case!F50/Input!F68 -> 0.036230815 | G74: =AVERAGE(B74:F74) -> 0.084971836
A76: Intangible Assets | G76: =Case!F51 -> 80
A78: Non current assets - Financial assets :
A79: i) Investments | B79: =Case!B53 -> 7851 | C79: =Case!C53 -> 7987 | D79: =Case!D53 -> 8296 | E79: =Case!E53 -> 18714 | F79: =Case!F53 -> 57912 | I79: =_xlfn.FORECAST.LINEAR(I3,$B$79:$F$79,$B$3:$F$3) -> 53406.7 | J79: =_xlfn.FORECAST.LINEAR(J3,$B$79:$F$79,$B$3:$F$3) -> 64491.6 | K79: =_xlfn.FORECAST.LINEAR(K3,$B$79:$F$79,$B$3:$F$3) -> 75576.5 | L79: =_xlfn.FORECAST.LINEAR(L3,$B$79:$F$79,$B$3:$F$3) -> 86661.4 | M79: =_xlfn.FORECAST.LINEAR(M3,$B$79:$F$79,$B$3:$F$3) -> 97746.3
A80: ii) Loans | B80: =Case!B54/Case!B57 -> 0.0081298412 | C80: =Case!C54/Case!C57 -> 0.019026502 | D80: =Case!D54/Case!D57 -> 0.0035264887 | E80: =Case!E54/Case!E57 -> 0.0052986834 | F80: =Case!F54/Case!F57 -> 0.0013695963 | G80: =AVERAGE(B80:F80) -> 0.0074702223
A81: iii) Other financial assets | G81: =Case!F55 -> 2350
A83: Other non current assets | B83: =Case!B56/Case!B18 -> 0.025721475 | C83: =Case!C56/Case!C18 -> 0.017045321 | D83: =Case!D56/Case!D18 -> 0.0095097772 | E83: =Case!E56/Case!E18 -> 0.0070489295 | F83: =Case!F56/Case!F18 -> 0.0085402107 | G83: =AVERAGE(B83:F83) -> 0.013573143
A85: 2. Inventories Scheduled
A86: Raw materials | B86: 21959 | C86: 50060 | D86: 9486 | E86: 47960 | F86: 54812 | I86: =$G$92/$G$97*SUM('Model- Income statement'!$G$27:$G$29) -> 28039.017 | J86: =$G$92/$G$97*SUM('Model- Income statement'!H27:H29) -> 4750.6142 | K86: =$G$92/$G$97*SUM('Model- Income statement'!I27:I29) -> 24966.02 | L86: =$G$92/$G$97*SUM('Model- Income statement'!J27:J29) -> 27159.24 | M86: =$G$92/$G$97*SUM('Model- Income statement'!K27:K29) -> 34853.46
A87: Work-in- progress | B87: 2755 | C87: 2969 | D87: 2803 | E87: 3450 | F87: 4698 | I87: =G93/$G$97*SUM('Model- Income statement'!$G$27:$G$29) -> 2548.6988 | J87: =G93/$G$97*SUM('Model- Income statement'!H28:H30) -> 27.57262 | K87: =G93/$G$97*SUM('Model- Income statement'!I28:I30) -> 402.56255 | L87: =G93/$G$97*SUM('Model- Income statement'!J28:J30) -> 433.48886 | M87: =G93/$G$97*SUM('Model- Income statement'!K28:K30) -> 566.40841
A88: Finished goods | B88: 11085 | C88: 15899 | D88: 19064 | E88: 13701 | F88: 20776 | I88: =G94/$G$97*SUM('Model- Income statement'!$G$27:$G$29) -> 12307.523 | J88: =G94/$G$97*SUM('Model- Income statement'!H29:H31) -> 243.14078 | K88: =G94/$G$97*SUM('Model- Income statement'!I29:I31) -> 2061.7705 | L88: =G94/$G$97*SUM('Model- Income statement'!J29:J31) -> 2220.9479 | M88: =G94/$G$97*SUM('Model- Income statement'!K29:K31) -> 2875.0915
A89: Stores, spares, packing and others | B89: 3335 | C89: 4006 | D89: 2713 | E89: 3974 | F89: 4904 | I89: =G95/$G$97*SUM('Model- Income statement'!$G$27:$G$29) -> 2909.4429 | J89: =G95/$G$97*SUM('Model- Income statement'!H30:H32) -> 287.03705 | K89: =G95/$G$97*SUM('Model- Income statement'!I30:I32) -> 719.43104 | L89: =G95/$G$97*SUM('Model- Income statement'!J30:J32) -> 763.07908 | M89: =G95/$G$97*SUM('Model- Income statement'!K30:K32) -> 927.93806
A90: Stock- in -trade | B90: 0 | C90: 0 | D90: 15371 | E90: 0 | F90: 0 | I90: =G96/$G$97*SUM('Model- Income statement'!$G$27:$G$29) -> 2443.7455 | J90: =G96/$G$97*SUM('Model- Income statement'!H31:H33) -> 234.62487 | K90: =G96/$G$97*SUM('Model- Income statement'!I31:I33) -> 574.40775 | L90: =G96/$G$97*SUM('Model- Income statement'!J31:J33) -> 608.37443 | M90: =G96/$G$97*SUM('Model- Income statement'!K31:K33) -> 737.78207
A91: Number of days outstanding:
A92: Raw materials | B92: =B86/SUM(Case!$B$28:$B$30)*$G$97 -> 50.032679 | C92: =C86/SUM(Case!$C$28:$C$30)*$G$97 -> 104.47892 | D92: =D86/SUM(Case!$D$28:$D$30)*$G$97 -> 20.2633 | E92: =E86/SUM(Case!$E$28:$E$30)*$G$97 -> 110.83646 | F92: =F86/SUM(Case!$F$28:$F$30)*$G$97 -> 91.123652 | G92: =AVERAGE(B92:F92) -> 75.347002
A93: Work in progress | B93: =B87/SUM(Case!$B$28:$B$30)*$G$97 -> 6.2771542 | C93: =C87/SUM(Case!$C$28:$C$30)*$G$97 -> 6.1965223 | D93: =D87/SUM(Case!$D$28:$D$30)*$G$97 -> 5.9875636 | E93: =E87/SUM(Case!$E$28:$E$30)*$G$97 -> 7.9730149 | F93: =F87/SUM(Case!$F$28:$F$30)*$G$97 -> 7.8103137 | G93: =AVERAGE(B93:F93) -> 6.8489138
A94: Finished goods | B94: =B88/SUM(Case!$B$28:$B$30)*$G$97 -> 25.256717 | C94: =C88/SUM(Case!$C$28:$C$30)*$G$97 -> 33.182387 | D94: =D88/SUM(Case!$D$28:$D$30)*$G$97 -> 40.723123 | E94: =E88/SUM(Case!$E$28:$E$30)*$G$97 -> 31.663269 | F94: =F88/SUM(Case!$F$28:$F$30)*$G$97 -> 34.539608 | G94: =AVERAGE(B94:F94) -> 33.073021
A95: Stores, spares, packing and others | B95: =B89/SUM(Case!$B$28:$B$30)*$G$97 -> 7.5986604 | C95: =C89/SUM(Case!$C$28:$C$30)*$G$97 -> 8.3608179 | D95: =D89/SUM(Case!$D$28:$D$30)*$G$97 -> 5.7953122 | E95: =E89/SUM(Case!$E$28:$E$30)*$G$97 -> 9.1839888 | F95: =F89/SUM(Case!$F$28:$F$30)*$G$97 -> 8.1527839 | G95: =AVERAGE(B95:F95) -> 7.8183126
A96: Stock- in -trade | B96: =B90/SUM(Case!$B$28:$B$30)*$G$97 -> 0 | C96: =C90/SUM(Case!$C$28:$C$30)*$G$97 -> 0 | D96: =D90/SUM(Case!$D$28:$D$30)*$G$97 -> 32.834406 | E96: =E90/SUM(Case!$E$28:$E$30)*$G$97 -> 0 | F96: =F90/SUM(Case!$F$28:$F$30)*$G$97 -> 0 | G96: =AVERAGE(B96:F96) -> 6.5668813
A97: No of days | G97: 365
A99: Current Assets - Financial Assets:
A100: Investments | B100: =Case!B61 -> 1202 | C100: =Case!C61 -> 0 | D100: =Case!D61 -> 701 | E100: =Case!E61 -> 23344 | F100: =Case!F61 -> 27403 | I100: =_xlfn.FORECAST.LINEAR(I3,B100:F100,B3:F3) -> 33253.8 | J100: =_xlfn.FORECAST.LINEAR(J3,C100:G100,C3:G3) -> 49560.2 | K100: =_xlfn.FORECAST.LINEAR(K3,D100:H100,D3:H3) -> 70553.333 | L100: =_xlfn.FORECAST.LINEAR(L3,E100:I100,E3:I3) -> 47819.867 | M100: =_xlfn.FORECAST.LINEAR(M3,F100:J100,F3:J3) -> 81053.4
A101: Trade Receivables (DTO) | C101: =Case!C18/(AVERAGE(Case!B62:C62)) -> 7.5168898 | D101: =Case!D18/(AVERAGE(Case!C62:D62)) -> 7.072172 | E101: =Case!E18/(AVERAGE(Case!D62:E62)) -> 9.6511567 | F101: =Case!F18/(AVERAGE(Case!E62:F62)) -> 12.468383 | G101: =AVERAGE(C101:F101) -> 9.1771503
A102: Other current assets | B102: =Case!B66/Case!B18 -> 0.046760527 | C102: =Case!C66/Case!C18 -> 0.058246853 | D102: =Case!D66/Case!D18 -> 0.064477394 | E102: =Case!E66/Case!E18 -> 0.052954998 | F102: =Case!F66/Case!F18 -> 0.050576016 | G102: =AVERAGE(B102:F102) -> 0.054603158
A103: Other bank balances | G103: =Case!F64 -> 479
A104: Other financial assets | G104: =Case!F65 -> 4442
A106: 3. Total Equity Schedule-
A107: Face Value | B107: 5 | C107: 5 | D107: 5 | E107: 5 | F107: 1 | I107: 1 | J107: 1 | K107: 1 | L107: 1 | M107: 1
A108: Opening No of Shares | B108: 739 | C108: =B110 -> 739 | D108: =C110 -> 725.65 | E108: =D110 -> 688.14216 | F108: =E110*5 -> 3440.7108 | I108: =F110 -> 3440.7108 | J108: =I110 -> 3440.7108 | K108: =J110 -> 3418.3508 | L108: =K110 -> 3418.3508 | M108: =L110 -> 3418.3508
A109: No of Buy Back Shares(in Lakhs) | B109: 0 | C109: =1335000/100000 -> 13.35 | D109: =3750784/100000 -> 37.50784 | E109: 0 | F109: 0 | I109: 0 | J109: =2236000/100000 -> 22.36
A110: No of Shares (in lakhs)/Current Year Closing | B110: =B108-B109 -> 739 | C110: =C108-C109 -> 725.65 | D110: =D108-D109 -> 688.14216 | E110: =E108-E109 -> 688.14216 | F110: =F108-F109 -> 3440.7108 | I110: =I108-I109 -> 3440.7108 | J110: =J108-J109 -> 3418.3508 | K110: =K108-K109 -> 3418.3508 | L110: =L108-L109 -> 3418.3508 | M110: =M108-M109 -> 3418.3508
A111: Equity Capital | B111: =B107*B110 -> 3695 | C111: =C107*C110 -> 3628.25 | D111: =D107*D110 -> 3440.7108 | E111: =E107*E110 -> 3440.7108 | F111: =F107*F110 -> 3440.7108 | I111: =I107*I110 -> 3440.7108 | J111: =J107*J110 -> 3418.3508 | K111: =K107*K110 -> 3418.3508 | L111: =L107*L110 -> 3418.3508 | M111: =M107*M110 -> 3418.3508
A112: a)Net Income | B112: =Case!B41 -> 22497 | C112: =Case!C41 -> 28911 | D112: =Case!D41 -> 29461 | E112: =Case!E41 -> 43262 | F112: =Case!F41 -> 73080 | I112: ='Model- Income statement'!G40 -> 192473.14 | J112: ='Model- Income statement'!H40 -> 352698.54 | K112: ='Model- Income statement'!I40 -> 305067.95 | L112: ='Model- Income statement'!J40 -> 359081.19 | M112: ='Model- Income statement'!K40 -> 400311.44
A113: b)Expected Dividend Paid(2023-2027) | B113: =544 -> 544 | C113: 554 | D113: 3124 | E113: 3096 | F113: 516 | I113: =$G$114*I112 -> 43306.457 | J113: =$G$114*J112 -> 79357.171 | K113: =$G$114*K112 -> 68640.288 | L113: =$G$114*L112 -> 80793.267 | M113: =$G$114*M112 -> 90070.074
A114: Dividend Payout Ratio | G114: =(20%+25%)/2 -> 0.225
A115: Reserves and Surplus Calculation/ Other Equity - | B115: =Case!B73 -> 129977 | C115: =Case!C73 -> 147492 | D115: =Case!D73 -> 147047 | E115: =Case!E73 -> 187213 | F115: =Case!F73 -> 259777 | I115: =F115+(I112-I113)-(804*J109) -> 390966.24 | J115: =I115+(J112-J113) -> 664307.61 | K115: =J115+(K112-K113) -> 900735.27 | L115: =K115+(L112-L113) -> 1179023.2 | M115: =L115+(M112-M113) -> 1489264.6
A116: Total Equity/Share Holders Fund | B116: =B111+B115 -> 133672 | C116: =C111+C115 -> 151120.25 | D116: =D111+D115 -> 150487.71 | E116: =E111+E115 -> 190653.71 | F116: =F111+F115 -> 263217.71 | I116: =I111+I115 -> 394406.95 | J116: =J111+J115 -> 667725.96 | K116: =K111+K115 -> 904153.62 | L116: =L111+L115 -> 1182441.5 | M116: =M111+M115 -> 1492682.9
A118: 2) Non current liabilities
A119: a) Financial liabilities
A120: i) Borrowings | B120: =Case!B78/Case!B49 -> 0.11715026 | C120: =Case!C78/Case!C49 -> 0.10323369 | D120: =Case!D78/Case!D49 -> 0.076937297 | E120: =Case!E78/Case!E49 -> 0.012424699 | F120: =Case!F78/Case!F49 -> 0.00036715502 | G120: =AVERAGE(B120:F120) -> 0.06202262
A121: b) Deffered tax liabilities (net) | G121: =Case!F79 -> 4368
A122: c) Other non current liabilities | B122: =Case!B80/Case!B28 -> 0 | C122: =Case!C80/Case!C28 -> 0 | D122: =Case!D80/Case!D28 -> 4.1292576e-05 | E122: =Case!E80/Case!E28 -> 2.9016627e-05 | F122: =Case!F80/Case!F28 -> 1.3165112e-05 | G122: =AVERAGE(D122:F122) -> 2.7824772e-05
A124: 3) Current liabilities
...

Sheet Model- Income statement
A2: Income Statement
A3: Particulars | B3: 2018 | C3: 2019 | D3: 2020 | E3: 2021 | F3: 2022 | G3: 2023 | H3: 2024 | I3: 2025 | J3: 2026 | K3: 2027
A4: I) Revenue from Operations:
A5: (i)Sale of Products
A6: (a) Garment | B6: 59729 | C6: 110164 | D6: 124982 | E6: 121693 | F6: 166911 | G6: =Input!I7 -> 203862.96 | H6: =Input!J7 -> 249892.97 | I6: =Input!K7 -> 307371.68 | J6: =Input!L7 -> 379308.61 | K6: =Input!M7 -> 469526.97
A7: (b) Yarn | B7: 132632 | C7: 145198 | D7: 126731 | E7: 122320 | F7: 181859 | G7: =Input!I11 -> 188587.78 | H7: =Input!J11 -> 195565.53 | I7: =Input!K11 -> 202801.46 | J7: =Input!L11 -> 210305.11 | K7: =Input!M11 -> 218086.4
A8: (c) Fabric | B8: 34746 | C8: 16653 | D8: 15647 | E8: 29597 | F8: 27895 | G8: =Input!I12 -> 29658.714 | H8: =Input!J12 -> 31533.942 | I8: =Input!K12 -> 33527.735 | J8: =Input!L12 -> 35647.589 | K8: =Input!M12 -> 37901.475
A9: (d) Cotton Waste | B9: 9067 | C9: 9930 | D9: 9752 | E9: 8432 | F9: 11408 | G9: =Input!I14 -> 12248.881 | H9: =Input!J14 -> 13151.744 | I9: =Input!K14 -> 14121.156 | J9: =Input!L14 -> 15162.024 | K9: =Input!M14 -> 16279.613
A10: (e) Accessories and Others | B10: 1397 | C10: 2609 | D10: 1696 | E10: 1752 | F10: 2144 | G10: =Input!I16 -> 2077.4078 | H10: =Input!J16 -> 2012.884 | I10: =Input!K16 -> 1950.3643 | J10: =Input!L16 -> 1889.7864 | K10: =Input!M16 -> 1831.09
A11: Total of Sale of Products (Gross) | B11: =SUM(B6:B10) -> 237571 | C11: =SUM(C6:C10) -> 284554 | D11: =SUM(D6:D10) -> 278808 | E11: =SUM(E6:E10) -> 283794 | F11: =SUM(F6:F10) -> 390217 | G11: =SUM(G6:G10) -> 436435.75 | H11: =SUM(H6:H10) -> 492157.07 | I11: =SUM(I6:I10) -> 559772.39 | ... K11: =SUM(K6:K10) -> 743625.55
A12: Less: Discount allowed | B12: 71 | C12: 763 | D12: 1556 | E12: 395 | F12: 722 | G12: =Input!I18 -> 1031.6678 | H12: =Input!J18 -> 1163.3845 | I12: =Input!K18 -> 1323.2169 | J12: =Input!L18 -> 1518.3306 | K12: =Input!M18 -> 1757.8178
A13: Total of Sale of Products (Net) | B13: =B11-B12 -> 237500 | C13: =C11-C12 -> 283791 | D13: =D11-D12 -> 277252 | E13: =E11-E12 -> 283399 | F13: =F11-F12 -> 389495 | G13: =G11-G12 -> 435404.08 | H13: =H11-H12 -> 490993.69 | I13: =I11-I12 -> 558449.17 | ... K13: =K11-K12 -> 741867.73
A14: (ii) Sale of Services
A15: Processing and fabrication income | B15: 7126 | C15: 4534 | D15: 2948 | E15: 4723 | F15: 5374 | G15: =Input!I22 -> 5642.7 | H15: =Input!J22 -> 5924.835 | I15: =Input!K22 -> 6221.0768 | J15: =Input!L22 -> 6532.1306 | K15: =Input!M22 -> 6858.7371
A16: (iii) Other Operating Revenues | B16: 6526 | C16: 9528 | D16: 9607 | E16: 7242 | F16: 12498 | G16: =F16*(1+Input!$G$24) -> 15459.68 | H16: =G16*(1+Input!$G$24) -> 19123.196 | I16: =H16*(1+Input!$G$24) -> 23654.863 | J16: =I16*(1+Input!$G$24) -> 29260.41 | K16: =J16*(1+Input!$G$24) -> 36194.317
A17: Total Revenue from Operations (i+ii+iii) | B17: =B13+B15+B16 -> 251152 | C17: =C13+C15+C16 -> 297853 | D17: =D13+D15+D16 -> 289807 | E17: =E13+E15+E16 -> 295364 | F17: =F13+F15+F16 -> 407367 | G17: =G13+G15+G16 -> 456506.46 | H17: =H13+H15+H16 -> 516041.72 | I17: =I13+I15+I16 -> 588325.11 | ... K17: =K13+K15+K16 -> 784920.79
A18: II) Other income
A19: (i) Dividend income from long term investments in subsidiaries | B19: 26 | C19: 26 | D19: 26 | E19: 26 | F19: 26 | G19: =Input!$G$27 -> 26 | H19: =Input!$G$27 -> 26 | I19: =Input!$G$27 -> 26 | J19: =Input!$G$27 -> 26 | K19: =Input!$G$27 -> 26
A20: (ii) Gain on sale of investment (net) | B20: 116 | C20: 181 | D20: 546 | E20: 359 | F20: 1359 | G20: =Input!$G$28 -> 0 | H20: =Input!$G$28 -> 0 | I20: =Input!$G$28 -> 0 | J20: =Input!$G$28 -> 0 | K20: =Input!$G$28 -> 0
A21: (iii) Net gain on sale of property, plant and equipment | B21: 30 | C21: 175 | D21: 215 | E21: 44 | F21: 296 | G21: =Input!$G$29 -> 0 | H21: =Input!$G$29 -> 0 | I21: =Input!$G$29 -> 0 | J21: =Input!$G$29 -> 0 | K21: =Input!$G$29 -> 0
A22: (iv) Rental income | B22: 227 | C22: 3049 | D22: 2582 | E22: 2826 | F22: 2947 | G22: =Input!$G$30*'Balance sheet'!G6 -> 2499.1907 | H22: =Input!$G$30*'Balance sheet'!H6 -> 2647.2594 | I22: =Input!$G$30*'Balance sheet'!I6 -> 2835.5708 | J22: =Input!$G$30*'Balance sheet'!J6 -> 3072.2955 | K22: =Input!$G$30*'Balance sheet'!K6 -> 3367.9034
A23: (v) Misc Other Income | B23: 1199 | C23: 306 | D23: 277 | E23: 541 | F23: 3835 | G23: =Input!$G$31 -> 3835 | H23: =Input!$G$31 -> 3835 | I23: =Input!$G$31 -> 3835 | J23: =Input!$G$31 -> 3835 | K23: =Input!$G$31 -> 3835
A24: Total of Other Income | B24: =SUM(B19:B23) -> 1598 | C24: =SUM(C19:C23) -> 3737 | D24: =SUM(D19:D23) -> 3646 | E24: =SUM(E19:E23) -> 3796 | F24: =SUM(F19:F23) -> 8463 | G24: =SUM(G19:G23) -> 6360.1907 | H24: =SUM(H19:H23) -> 6508.2594 | I24: =SUM(I19:I23) -> 6696.5708 | ... K24: =SUM(K19:K23) -> 7228.9034
A25: III) Total income (I+II) | B25: =B17+B24 -> 252750 | C25: =C17+C24 -> 301590 | D25: =D17+D24 -> 293453 | E25: =E17+E24 -> 299160 | F25: =F17+F24 -> 415830 | G25: =G17+G24 -> 462866.65 | H25: =H17+H24 -> 522549.98 | I25: =I17+I24 -> 595021.68 | ... K25: =K17+K24 -> 792149.69
A26: IV) Expenses:
A27: a) Cost Of Materials Consumed | B27: 164709 | C27: 179914 | D27: 169522 | E27: 137852 | F27: 227875 | G27: =Input!I33 -> 139559.08 | H27: =Input!J33 -> 27230.715 | I27: =Input!K33 -> 125750.03 | J27: =Input!L33 -> 137095.9 | K27: =Input!M33 -> 175254.05
A28: b) Purchase of stock in trade | B28: 0 | C28: 0 | D28: 19718 | E28: 0 | F28: 0 | G28: 0 | H28: 0 | I28: 0 | J28: 0 | K28: 0
A29: c) Changes in inventories of finished goods, stock in trade and work in progress | B29: -4513 | C29: -5028 | D29: -18370 | E29: 20087 | F29: -8323 | G29: =G17*Input!$G$45 -> -3730.9611 | H29: =H17*Input!$G$45 -> -4217.5342 | I29: =I17*Input!$G$45 -> -4808.2959 | J29: =J17*Input!$G$45 -> -5529.6502 | K29: =K17*Input!$G$45 -> -6415.0438
A30: d) Employee benefits expense | B30: 23305 | C30: 37341 | D30: 38325 | E30: 38479 | F30: 43289 | G30: =Input!$G$47*G27 -> 29146.044 | H30: =Input!$G$47*H27 -> 5686.9652 | I30: =Input!$G$47*I27 -> 26262.111 | J30: =Input!$G$47*J27 -> 28631.625 | K30: =Input!$G$47*K27 -> 36600.717
A31: e) Finance costs | B31: 3049 | C31: 3586 | D31: 3541 | E31: 1961 | F31: 1339 | G31: =Input!$G$47*'Balance sheet'!G35 -> 1146.0181 | H31: =Input!$G$47*'Balance sheet'!H35 -> 1213.9158 | I31: =Input!$G$47*'Balance sheet'!I35 -> 1300.2671 | J31: =Input!$G$47*'Balance sheet'!J35 -> 1408.8186 | K31: =Input!$G$47*'Balance sheet'!K35 -> 1544.3712
A32: f) Depreciation and amortisation expense | B32: 10497 | C32: 9583 | D32: 9891 | E32: 9792 | F32: 7565 | G32: =F32*(1+Input!$G$43) -> 7012.0516 | H32: =G32*(1+Input!$G$43) -> 6499.5199 | I32: =H32*(1+Input!$G$43) -> 6024.4507 | J32: =I32*(1+Input!$G$43) -> 5584.1056 | K32: =J32*(1+Input!$G$43) -> 5175.9467
A33: g) Other expenses | B33: 24747 | C33: 34919 | D33: 33159 | E33: 32507 | F33: 46136 | G33: =Input!$G$51*G27 -> 27303.607 | H33: =Input!$G$51*H27 -> 5327.4696 | I33: =Input!$G$51*I27 -> 24601.979 | J33: =Input!$G$51*J27 -> 26821.707 | K33: =Input!$G$51*K27 -> 34287.041
A34: V) Total expenses | B34: =B27+SUM(B28:B33) -> 221794 | C34: =C27+SUM(C28:C33) -> 260315 | D34: =D27+SUM(D28:D33) -> 255786 | E34: =E27+SUM(E28:E33) -> 240678 | F34: =F27+SUM(F28:F33) -> 317881 | G34: =G27+SUM(G28:G33) -> 200435.84 | H34: =H27+SUM(H28:H33) -> 41741.051 | I34: =I27+SUM(I28:I33) -> 179130.55 | ... K34: =K27+SUM(K28:K33) -> 246447.08
A35: VI) Profit before tax (III-V) | B35: =B25-B34 -> 30956 | C35: =C25-C34 -> 41275 | D35: =D25-D34 -> 37667 | E35: =E25-E34 -> 58482 | F35: =F25-F34 -> 97949 | G35: =G25-G34 -> 262430.81 | H35: =H25-H34 -> 480808.93 | I35: =I25-I34 -> 415891.14 | ... K35: =K25-K34 -> 545702.61
A36: VII) Tax expense
A37: (i) Current tax | B37: 8263 | C37: 12453 | D37: 9140 | E37: 15654 | F37: 24795 | G37: =IF(G35>0,G35*Input!$G$54,0) -> 69883.674 | H37: =IF(H35>0,H35*Input!$G$54,0) -> 128036.39 | I37: =IF(I35>0,I35*Input!$G$54,0) -> 110749.19 | J37: =IF(J35>0,J35*Input!$G$54,0) -> 130352.93 | K37: =IF(K35>0,K35*Input!$G$54,0) -> 145317.17
A38: (ii) Deffered tax | B38: 196 | C38: -89 | D38: -934 | E38: -434 | F38: 74 | G38: =Input!$G$55 -> 74 | H38: =Input!$G$55 -> 74 | I38: =Input!$G$55 -> 74 | J38: =Input!$G$55 -> 74 | K38: =Input!$G$55 -> 74
A39: Income tax expense | B39: =B37+B38 -> 8459 | C39: =C37+C38 -> 12364 | D39: =D37+D38 -> 8206 | E39: =E37+E38 -> 15220 | F39: =F37+F38 -> 24869 | G39: =G37+G38 -> 69957.674 | H39: =H37+H38 -> 128110.39 | I39: =I37+I38 -> 110823.19 | ... K39: =K37+K38 -> 145391.17
A40: VIII) Profit after tax (VI-VII) | B40: =B35-B39 -> 22497 | C40: =C35-C39 -> 28911 | D40: =D35-D39 -> 29461 | E40: =E35-E39 -> 43262 | F40: =F35-F39 -> 73080 | G40: =G35-G39 -> 192473.14 | H40: =H35-H39 -> 352698.54 | I40: =I35-I39 -> 305067.95 | ... K40: =K35-K39 -> 400311.44

Sheet Balance sheet
A2: Balance Sheet
A3: Particulars | B3: 2018 | C3: 2019 | D3: 2020 | E3: 2021 | F3: 2022 | G3: 2023 | H3: 2024 | I3: 2025 | J3: 2026 | K3: 2027
A4: Assets
A5: 1) Non current assets
A6: a) Property, plant and equipment | B6: 86436 | C6: 79383 | D6: 86551 | E6: 79680 | F6: 84433 | G6: =Input!I70 -> 88474.85 | H6: =Input!J70 -> 93716.69 | I6: =Input!K70 -> 100383.17 | J6: =Input!L70 -> 108763.56 | K6: =Input!M70 -> 119228.5
A7: b) Capital work in progress | B7: 10 | C7: 441 | D7: 579 | E7: 1742 | F7: 491 | G7: =Input!$G$74*Input!I68 -> 1146.8246 | H7: =Input!$G$74*Input!J68 -> 1296.3876 | I7: =Input!$G$74*Input!K68 -> 1477.9763 | J7: =Input!$G$74*Input!L68 -> 1699.7065 | K7: =Input!$G$74*Input!M68 -> 1971.8592
A8: c) Intangible assets | B8: 18 | C8: 20 | D8: 105 | E8: 95 | F8: 80 | G8: =Input!$G$76 -> 80 | H8: =Input!$G$76 -> 80 | I8: =Input!$G$76 -> 80 | J8: =Input!$G$76 -> 80 | K8: =Input!$G$76 -> 80
A9: d) Financial assets
A10: i) Investments | B10: 7851 | C10: 7987 | D10: 8296 | E10: 18714 | F10: 57912 | G10: =Input!I79 -> 53406.7 | H10: =Input!J79 -> 64491.6 | I10: =Input!K79 -> 75576.5 | J10: =Input!L79 -> 86661.4 | K10: =Input!M79 -> 97746.3
A11: ii) Loans | B11: 826 | C11: 1802 | D11: 352 | E11: 555 | F11: 204 | G11: =G14*Input!$G$80 -> 1141.4203 | H11: =H14*Input!$G$80 -> 1271.5102 | I11: =I14*Input!$G$80 -> 1413.8661 | J11: =J14*Input!$G$80 -> 1571.0561 | K11: =K14*Input!$G$80 -> 1746.3651
A12: iii) Other financial assets | B12: 0 | C12: 0 | D12: 1177 | E12: 1875 | F12: 2350 | G12: =Input!$G$81 -> 2350 | H12: =Input!$G$81 -> 2350 | I12: =Input!$G$81 -> 2350 | J12: =Input!$G$81 -> 2350 | K12: =Input!$G$81 -> 2350
A13: e) Other non current assets | B13: 6460 | C13: 5077 | D13: 2756 | E13: 2082 | F13: 3479 | G13: =Input!$G$83*'Model- Income statement'!G17 -> 6196.2273 | H13: =Input!$G$83*'Model- Income statement'!H17 -> 7004.3079 | I13: =Input!$G$83*'Model- Income statement'!I17 -> 7985.4208 | J13: =Input!$G$83*'Model- Income statement'!J17 -> 9183.4164 | K13: =Input!$G$83*'Model- Income statement'!K17 -> 10653.842
A14: Total non current assets | B14: =SUM(B6:B13) -> 101601 | C14: =SUM(C6:C13) -> 94710 | D14: =SUM(D6:D13) -> 99816 | E14: =SUM(E6:E13) -> 104743 | F14: =SUM(F6:F13) -> 148949 | G14: =SUM(G6:G13) -> 152796.02 | H14: =SUM(H6:H13) -> 170210.5 | I14: =SUM(I6:I13) -> 189266.94 | ... K14: =SUM(K6:K13) -> 233776.86
A15: 2) Current Assets
A16: a) Inventories | B16: 39134 | C16: 72934 | D16: 49437 | E16: 69085 | F16: 85190 | G16: =SUM(Input!I86:I90) -> 48248.428 | H16: =SUM(Input!J86:J90) -> 5542.9895 | I16: =SUM(Input!K86:K90) -> 28724.192 | J16: =SUM(Input!L86:L90) -> 31185.13 | K16: =SUM(Input!M86:M90) -> 39960.68
A17: b) Financial assets
A18: (i) Investment | B18: 1202 | C18: 0 | D18: 701 | E18: 23344 | F18: 27403 | G18: =Input!I100 -> 33253.8 | H18: =Input!J100 -> 49560.2 | I18: =Input!K100 -> 70553.333 | J18: =Input!L100 -> 47819.867 | K18: =Input!M100 -> 81053.4
A19: (ii) Trade receivables | B19: 32419 | C19: 46830 | D19: 35127 | E19: 26081 | F19: 39263 | G19: =(2*'Model- Income statement'!G17/Input!$G$101)-F19 -> 60224.628 | H19: =(2*'Model- Income statement'!H17/Input!$G$101)-G19 -> 52237.672 | I19: =(2*'Model- Income statement'!I17/Input!$G$101)-H19 -> 75977.535 | J19: =(2*'Model- Income statement'!J17/Input!$G$101)-I19 -> 71472.885 | K19: =(2*'Model- Income statement'!K17/Input!$G$101)-J19 -> 99586.924
A20: (iii) Cash and cash equivalents | B20: 1641 | C20: 5633 | D20: 14533 | E20: 4503 | F20: 9561 | G20: ='Cash flow'!B46 -> 148041.71 | H20: ='Cash flow'!C46 -> 401687.57 | I20: ='Cash flow'!D46 -> 687582.99 | J20: ='Cash flow'!E46 -> 842342.7 | K20: ='Cash flow'!F46 -> 1236207.9
A21: (iv) Other bank balances | B21: 1100 | C21: 1044 | D21: 171 | E21: 787 | F21: 479 | G21: =Input!$G$103 -> 479 | H21: =Input!$G$103 -> 479 | I21: =Input!$G$103 -> 479 | J21: =Input!$G$103 -> 479 | K21: =Input!$G$103 -> 479
A22: (v) Other financial assets | B22: 4196 | C22: 1221 | D22: 249 | E22: 4359 | F22: 4442 | G22: =Input!$G$104 -> 4442 | H22: =Input!$G$104 -> 4442 | I22: =Input!$G$104 -> 4442 | J22: =Input!$G$104 -> 4442 | K22: =Input!$G$104 -> 4442
A23: (c) Other current assets | B23: 11744 | C23: 17349 | D23: 18686 | E23: 15641 | F23: 20603 | G23: =Input!$G$102*'Model- Income statement'!G17 -> 24926.694 | H23: =Input!$G$102*'Model- Income statement'!H17 -> 28177.507 | I23: =Input!$G$102*'Model- Income statement'!I17 -> 32124.409 | J23: =Input!$G$102*'Model- Income statement'!J17 -> 36943.805 | K23: =Input!$G$102*'Model- Income statement'!K17 -> 42859.153
A24: Total current assets | B24: =SUM(B16:B23) -> 91436 | C24: =SUM(C16:C23) -> 145011 | D24: =SUM(D16:D23) -> 118904 | E24: =SUM(E16:E23) -> 143800 | F24: =SUM(F16:F23) -> 186941 | G24: =SUM(G16:G23) -> 319616.26 | H24: =SUM(H16:H23) -> 542126.94 | I24: =SUM(I16:I23) -> 899883.46 | ... K24: =SUM(K16:K23) -> 1504589.1
A25: Total Assets | B25: =SUM(B14+B24) -> 193037 | C25: =SUM(C14+C24) -> 239721 | D25: =SUM(D14+D24) -> 218720 | E25: =SUM(E14+E24) -> 248543 | F25: =SUM(F14+F24) -> 335890 | G25: =SUM(G14+G24) -> 472412.28 | H25: =SUM(H14+H24) -> 712337.43 | I25: =SUM(I14+I24) -> 1089150.4 | ... K25: =SUM(K14+K24) -> 1738365.9
A27: Equity and Liabilities
A28: 1) Equity
A29: a) Equity share capital | B29: 3695 | C29: 3628 | D29: 3441 | E29: 3441 | F29: 3441 | G29: =Input!I111 -> 3440.7108 | H29: =Input!J111 -> 3418.3508 | I29: =Input!K111 -> 3418.3508 | J29: =Input!L111 -> 3418.3508 | K29: =Input!M111 -> 3418.3508
A30: b) Other equity | B30: 129977 | C30: 147492 | D30: 147047 | E30: 187213 | F30: 259777 | G30: =Input!I115 -> 390966.24 | H30: =Input!J115 -> 664307.61 | I30: =Input!K115 -> 900735.27 | J30: =Input!L115 -> 1179023.2 | K30: =Input!M115 -> 1489264.6
A31: Total Equity | B31: =SUM(B29,B30) -> 133672 | C31: =SUM(C29,C30) -> 151120 | D31: =SUM(D29,D30) -> 150488 | E31: =SUM(E29,E30) -> 190654 | F31: =SUM(F29,F30) -> 263218 | G31: =G29+G30 -> 394406.95 | H31: =H29+H30 -> 667725.96 | I31: =I29+I30 -> 904153.62 | J31: =J29+J30 -> 1182441.5 | K31: =K29+K30 -> 1492682.9
A32: Liabilities
A33: 2) Non current liabilities
A34: a) Financial liabilities
A35: i) Borrowings | B35: 10126 | C35: 8195 | D35: 6659 | E35: 990 | F35: 31 | G35: =Input!$G$120*'Balance sheet'!G6 -> 5487.442 | H35: =Input!$G$120*'Balance sheet'!H6 -> 5812.5547 | I35: =Input!$G$120*'Balance sheet'!I6 -> 6226.0276 | J35: =Input!$G$120*'Balance sheet'!J6 -> 6745.8012 | K35: =Input!$G$120*'Balance sheet'!K6 -> 7394.8638
A36: b) Deffered tax liabilities (net) | B36: 5750 | C36: 5661 | D36: 4727 | E36: 4294 | F36: 4368 | G36: =Input!$G$121 -> 4368 | H36: =Input!$G$121 -> 4368 | I36: =Input!$G$121 -> 4368 | J36: =Input!$G$121 -> 4368 | K36: =Input!$G$121 -> 4368
A37: c) Other non current liabilities | B37: 0 | C37: 0 | D37: 7 | E37: 4 | F37: 3 | G37: =Input!$G$122*'Model- Income statement'!G27 -> 3.8831994 | H37: =Input!$G$122*'Model- Income statement'!H27 -> 0.75768842 | I37: =Input!$G$122*'Model- Income statement'!I27 -> 3.498966 | J37: =Input!$G$122*'Model- Income statement'!J27 -> 3.8146621 | K37: =Input!$G$122*'Model- Income statement'!K27 -> 4.8764039
A38: Total non current liabilities | B38: =SUM(B35:B37) -> 15876 | C38: =SUM(C35:C37) -> 13856 | D38: =SUM(D35:D37) -> 11393 | E38: =SUM(E35:E37) -> 5288 | F38: =SUM(F35:F37) -> 4402 | G38: =SUM(G35:G37) -> 9859.3252 | H38: =SUM(H35:H37) -> 10181.312 | I38: =SUM(I35:I37) -> 10597.527 | ... K38: =SUM(K35:K37) -> 11767.74
A39: 3) Current liabilities
A40: a) Financial liabilities
A41: i) Borrowings | B41: 22822 | C41: 55241 | D41: 39876 | E41: 30579 | F41: 41754 | G41: =G46*Input!$G$126 -> 30504.181 | H41: =H46*Input!$G$126 -> 18786.401 | I41: =I46*Input!$G$126 -> 54707.526 | J41: =J46*Input!$G$126 -> 21365.817 | K41: =K46*Input!$G$126 -> 68038.16
A42: ii) Trade payables | B42: 13749 | C42: 12350 | D42: 10574 | E42: =881+9534 -> 10415 | F42: 12406 | G42: =(2*'Model- Income statement'!G27/Input!$G$127)-F42 -> 5694.0968 | H42: =(2*'Model- Income statement'!H27/Input!$G$127)-G42 -> -2162.4127 | I42: =(2*'Model- Income statement'!I27/Input!$G$127)-H42 -> 18471.547 | J42: =(2*'Model- Income statement'!J27/Input!$G$127)-I42 -> -690.91173 | K42: =(2*'Model- Income statement'!K27/Input!$G$127)-J42 -> 23420.464
A43: iii) Other financial liabilities | B43: 3150 | C43: 3192 | D43: 3592 | E43: 5020 | F43: 43 | G43: =Input!I128 -> 5842 | H43: =Input!J128 -> 6443 | I43: =Input!K128 -> 7044 | J43: =Input!L128 -> 7645 | K43: =Input!M128 -> 8246
A44: b) Other current liabilities | B44: 3762 | C44: 2915 | D44: 2481 | E44: 4265 | F44: 12395 | G44: =Case!B28*Input!$G$129 -> 4579.2584 | H44: =Case!C28*Input!$G$129 -> 5001.9896 | I44: =Case!D28*Input!$G$129 -> 4713.07 | J44: =Case!E28*Input!$G$129 -> 3832.577 | K44: =Case!F28*Input!$G$129 -> 6335.4067
A45: c) Current tax liabilities (net) | B45: 6 | C45: 1047 | D45: 316 | E45: 2322 | F45: 1672 | G45: =Input!$G$130 -> 1672 | H45: =Input!$G$130 -> 1672 | I45: =Input!$G$130 -> 1672 | J45: =Input!$G$130 -> 1672 | K45: =Input!$G$130 -> 1672
A46: Total current liabilities | B46: =SUM(B41:B45) -> 43489 | C46: =SUM(C41:C45) -> 74745 | D46: =SUM(D41:D45) -> 56839 | E46: =SUM(E41:E45) -> 52601 | F46: =SUM(F41:F45) -> 68270 | G46: =SUM(G41:G45) -> 48291.536 | H46: =SUM(H41:H45) -> 29740.978 | I46: =SUM(I41:I45) -> 86608.144 | ... K46: =SUM(K41:K45) -> 107712.03
A47: Total liabilities | B47: =SUM(B38,B46) -> 59365 | C47: =SUM(C38,C46) -> 88601 | D47: =SUM(D38,D46) -> 68232 | E47: =SUM(E38,E46) -> 57889 | F47: =SUM(F38,F46) -> 72672 | G47: =SUM(G38,G46) -> 58150.861 | H47: =SUM(H38,H46) -> 39922.29 | I47: =SUM(I38,I46) -> 97205.67 | ... K47: =SUM(K38,K46) -> 119479.77
A48: Total Equity and Liabilities | B48: =SUM(B47,B31) -> 193037 | C48: =SUM(C47,C31) -> 239721 | D48: =SUM(D47,D31) -> 218720 | E48: =SUM(E47,E31) -> 248543 | F48: =SUM(F47,F31) -> 335890 | G48: =SUM(G47,G31) -> 452557.82 | H48: =SUM(H47,H31) -> 707648.25 | I48: =SUM(I47,I31) -> 1001359.3 | ... K48: =SUM(K47,K31) -> 1612162.7

Sheet Cash flow
A1: Cashflow Statement
A2: Particulars | B2: 2023 | C2: 2024 | D2: 2025 | E2: 2026 | F2: 2027
A3: Net Profit Before Tax and Extraordinary Items | B3: ='Model- Income statement'!G35 -> 262430.81 | C3: ='Model- Income statement'!H35 -> 480808.93 | D3: ='Model- Income statement'!I35 -> 415891.14 | E3: ='Model- Income statement'!J35 -> 489508.12 | F3: ='Model- Income statement'!K35 -> 545702.61
A4: Add/Less: Non-cash operating income/expense
A5: Add: Depriciation | B5: ='Model- Income statement'!G32 -> 7012.0516 | C5: ='Model- Income statement'!H32 -> 6499.5199 | D5: ='Model- Income statement'!I32 -> 6024.4507 | E5: ='Model- Income statement'!J32 -> 5584.1056 | F5: ='Model- Income statement'!K32 -> 5175.9467
A6: Add: Finance Cost | B6: ='Model- Income statement'!G31 -> 1146.0181 | C6: ='Model- Income statement'!H31 -> 1213.9158 | D6: ='Model- Income statement'!I31 -> 1300.2671 | E6: ='Model- Income statement'!J31 -> 1408.8186 | F6: ='Model- Income statement'!K31 -> 1544.3712
A7: Less: Dividend Income | B7: =-'Model- Income statement'!G19 -> -26 | C7: =-'Model- Income statement'!H19 -> -26 | D7: =-'Model- Income statement'!I19 -> -26 | E7: =-'Model- Income statement'!J19 -> -26 | F7: =-'Model- Income statement'!K19 -> -26
A8: Less: Rental Income | B8: =-'Model- Income statement'!G22 -> -2499.1907 | C8: =-'Model- Income statement'!H22 -> -2647.2594 | D8: =-'Model- Income statement'!I22 -> -2835.5708 | E8: =-'Model- Income statement'!J22 -> -3072.2955 | F8: =-'Model- Income statement'!K22 -> -3367.9034
A9: Less: Net gain on sale of property, plant and equipment | B9: =-'Model- Income statement'!G21 -> 0 | C9: =-'Model- Income statement'!H21 -> 0 | D9: =-'Model- Income statement'!I21 -> 0 | E9: =-'Model- Income statement'!J21 -> 0 | F9: =-'Model- Income statement'!K21 -> 0
A10: Less: Gain on sale of investments | B10: =-'Model- Income statement'!G20 -> 0 | C10: =-'Model- Income statement'!H20 -> 0 | D10: =-'Model- Income statement'!I20 -> 0 | E10: =-'Model- Income statement'!J20 -> 0 | F10: =-'Model- Income statement'!K20 -> 0
A11: Operating Profit before working capital Changes | B11: =SUM(B3:B10) -> 268063.69 | C11: =SUM(C3:C10) -> 485849.1 | D11: =SUM(D3:D10) -> 420354.29 | E11: =SUM(E3:E10) -> 493402.75 | F11: =SUM(F3:F10) -> 549029.02
A13: Adjustments for increase / decrease in current assets:
A14: Inventories | B14: =-('Balance sheet'!G16-'Balance sheet'!F16) -> 36941.572 | C14: =-('Balance sheet'!H16-'Balance sheet'!G16) -> 42705.438 | D14: =-('Balance sheet'!I16-'Balance sheet'!H16) -> -23181.202 | E14: =-('Balance sheet'!J16-'Balance sheet'!I16) -> -2460.9384 | F14: =-('Balance sheet'!K16-'Balance sheet'!J16) -> -8775.5497
A15: Trade Receivables | B15: =-('Balance sheet'!G19-'Balance sheet'!F19) -> -20961.628 | C15: =-('Balance sheet'!H19-'Balance sheet'!G19) -> 7986.9561 | D15: =-('Balance sheet'!I19-'Balance sheet'!H19) -> -23739.863 | E15: =-('Balance sheet'!J19-'Balance sheet'!I19) -> 4504.6503 | F15: =-('Balance sheet'!K19-'Balance sheet'!J19) -> -28114.039
A16: Other financial assets | B16: ='Balance sheet'!G22-'Balance sheet'!F22 -> 0 | C16: ='Balance sheet'!H22-'Balance sheet'!G22 -> 0 | D16: ='Balance sheet'!I22-'Balance sheet'!H22 -> 0 | E16: ='Balance sheet'!J22-'Balance sheet'!I22 -> 0 | F16: ='Balance sheet'!K22-'Balance sheet'!J22 -> 0
A17: Other current assets | B17: =-('Balance sheet'!G23-'Balance sheet'!F23) -> -4323.6942 | C17: =-('Balance sheet'!H23-'Balance sheet'!G23) -> -3250.8131 | D17: =-('Balance sheet'!I23-'Balance sheet'!H23) -> -3946.9016 | E17: =-('Balance sheet'!J23-'Balance sheet'!I23) -> -4819.3957 | F17: =-('Balance sheet'!K23-'Balance sheet'!J23) -> -5915.3488
A18: Adjustments for increase / decrease in current liabilities
A19: Trade Paybles | B19: =('Balance sheet'!G42-'Balance sheet'!F42) -> -6711.9032 | C19: =('Balance sheet'!H42-'Balance sheet'!G42) -> -7856.5095 | D19: =('Balance sheet'!I42-'Balance sheet'!H42) -> 20633.96 | E19: =('Balance sheet'!J42-'Balance sheet'!I42) -> -19162.459 | F19: =('Balance sheet'!K42-'Balance sheet'!J42) -> 24111.375
A20: Other Financial Liabilities | B20: =('Balance sheet'!G43-'Balance sheet'!F43) -> 5799 | C20: =('Balance sheet'!H43-'Balance sheet'!G43) -> 601 | D20: =('Balance sheet'!I43-'Balance sheet'!H43) -> 601 | E20: =('Balance sheet'!J43-'Balance sheet'!I43) -> 601 | F20: =('Balance sheet'!K43-'Balance sheet'!J43) -> 601
A21: Other curret liabilities | B21: =('Balance sheet'!G46-'Balance sheet'!F46) -> -19978.464 | C21: =('Balance sheet'!H46-'Balance sheet'!G46) -> -18550.558 | D21: =('Balance sheet'!I46-'Balance sheet'!H46) -> 56867.166 | E21: =('Balance sheet'!J46-'Balance sheet'!I46) -> -52783.661 | F21: =('Balance sheet'!K46-'Balance sheet'!J46) -> 73887.548
A23: Cash generated from operating activities | B23: =SUM(B11:B21) -> 258828.58 | C23: =SUM(C11:C21) -> 507484.62 | D23: =SUM(D11:D21) -> 447588.44 | E23: =SUM(E11:E21) -> 419281.94 | F23: =SUM(F11:F21) -> 604824.01
A24: Net income tax paid | B24: =-'Model- Income statement'!G39 -> -69957.674 | C24: =-'Model- Income statement'!H39 -> -128110.39 | D24: =-'Model- Income statement'!I39 -> -110823.19 | E24: =-'Model- Income statement'!J39 -> -130426.93 | F24: =-'Model- Income statement'!K39 -> -145391.17
A25: Cash from Operating Activities | B25: =SUM(B23:B24) -> 188870.9 | C25: =SUM(C23:C24) -> 379374.23 | D25: =SUM(D23:D24) -> 336765.25 | E25: =SUM(E23:E24) -> 288855.01 | F25: =SUM(F23:F24) -> 459432.84
A27: Cash from Investing activity
A29: Purchase/ Sales of Fixed asset -PPE | B29: =-('Balance sheet'!G6-'Balance sheet'!F6) -> -4041.8497 | C29: =-('Balance sheet'!H6-'Balance sheet'!G6) -> -5241.8401 | D29: =-('Balance sheet'!I6-'Balance sheet'!H6) -> -6666.4851 | E29: =-('Balance sheet'!J6-'Balance sheet'!I6) -> -8380.3883 | F29: =-('Balance sheet'!K6-'Balance sheet'!J6) -> -10464.933
A30: Investment | B30: =-('Balance sheet'!G10-'Balance sheet'!F10) -> 4505.3 | C30: =-('Balance sheet'!H10-'Balance sheet'!G10) -> -11084.9 | D30: =-('Balance sheet'!I10-'Balance sheet'!H10) -> -11084.9 | E30: =-('Balance sheet'!J10-'Balance sheet'!I10) -> -11084.9 | F30: =-('Balance sheet'!K10-'Balance sheet'!J10) -> -11084.9
A31: Dividend income from long term investments in subsidiaries | B31: ='Model- Income statement'!G19 -> 26 | C31: ='Model- Income statement'!H19 -> 26 | D31: ='Model- Income statement'!I19 -> 26 | E31: ='Model- Income statement'!J19 -> 26 | F31: ='Model- Income statement'!K19 -> 26
A32: Other Non-current assets | B32: =-('Balance sheet'!G13-'Balance sheet'!F13) -> -2717.2273 | C32: =-('Balance sheet'!H13-'Balance sheet'!G13) -> -808.08057 | D32: =-('Balance sheet'!I13-'Balance sheet'!H13) -> -981.11284 | E32: =-('Balance sheet'!J13-'Balance sheet'!I13) -> -1197.9957 | F32: =-('Balance sheet'!K13-'Balance sheet'!J13) -> -1470.4255
A33: Intangible asset | B33: =-('Balance sheet'!G8-'Balance sheet'!F8) -> 0 | C33: =-('Balance sheet'!H8-'Balance sheet'!G8) -> 0 | D33: =-('Balance sheet'!I8-'Balance sheet'!H8) -> 0 | E33: =-('Balance sheet'!J8-'Balance sheet'!I8) -> 0 | F33: =-('Balance sheet'!K8-'Balance sheet'!J8) -> 0
A34: Net cash used in investing activities (B) | B34: =SUM(B29:B33) -> -2227.777 | C34: =SUM(C29:C33) -> -17108.821 | D34: =SUM(D29:D33) -> -18706.498 | E34: =SUM(E29:E33) -> -20637.284 | F34: =SUM(F29:F33) -> -22994.259
A36: Cash from Financing Activity
A37: Long Term Borrowings | B37: =('Balance sheet'!G35-'Balance sheet'!F35) -> 5456.442 | C37: =('Balance sheet'!H35-'Balance sheet'!G35) -> 325.11266 | D37: =('Balance sheet'!I35-'Balance sheet'!H35) -> 413.47288 | E37: =('Balance sheet'!J35-'Balance sheet'!I35) -> 519.77364 | F37: =('Balance sheet'!K35-'Balance sheet'!J35) -> 649.06259
A38: Short Term Borrowings | B38: =('Balance sheet'!G41-'Balance sheet'!F41) -> -11249.819 | C38: =('Balance sheet'!H41-'Balance sheet'!G41) -> -11717.78 | D38: =('Balance sheet'!I41-'Balance sheet'!H41) -> 35921.125 | E38: =('Balance sheet'!J41-'Balance sheet'!I41) -> -33341.709 | F38: =('Balance sheet'!K41-'Balance sheet'!J41) -> 46672.343
A39: Dividend Paid | B39: =-Input!I113 -> -43306.457 | C39: =-Input!J113 -> -79357.171 | D39: =-Input!K113 -> -68640.288 | E39: =-Input!L113 -> -80793.267 | F39: =-Input!M113 -> -90070.074
A40: Share buyback | C40: =-805*Input!J109 -> -17999.8
A41: Loan | B41: =('Balance sheet'!G11-'Balance sheet'!F11) -> 937.42026 | C41: =('Balance sheet'!H11-'Balance sheet'!G11) -> 130.08999 | D41: =('Balance sheet'!I11-'Balance sheet'!H11) -> 142.35586 | E41: =('Balance sheet'!J11-'Balance sheet'!I11) -> 157.18994 | F41: =('Balance sheet'!K11-'Balance sheet'!J11) -> 175.30909
A42: Net cash used in financing activities (C) | B42: =SUM(B37:B41) -> -48162.413 | C42: =SUM(C37:C41) -> -108619.55 | D42: =SUM(D37:D41) -> -32163.334 | E42: =SUM(E37:E41) -> -113458.01 | F42: =SUM(F37:F41) -> -42573.359
A44: Cash and cash equivalent generated during the year | B44: =B25+B34+B42 -> 138480.71 | C44: =C25+C34+C42 -> 253645.86 | D44: =D25+D34+D42 -> 285895.42 | E44: =E25+E34+E42 -> 154759.72 | F44: =F25+F34+F42 -> 393865.22
A45: ADD: cash and CE at the benginning of the period | B45: ='Balance sheet'!F20 -> 9561 | C45: ='Balance sheet'!G20 -> 148041.71 | D45: ='Balance sheet'!H20 -> 401687.57 | E45: ='Balance sheet'!I20 -> 687582.99 | F45: ='Balance sheet'!J20 -> 842342.7
A46: cash and CE at the end of the period | B46: =B44+B45 -> 148041.71 | C46: =C44+C45 -> 401687.57 | D46: =D44+D45 -> 687582.99 | E46: =E44+E45 -> 842342.7 | F46: =F44+F45 -> 1236207.9

Sheet Ratios
A2: Sr. No. | B2: Particulars | C2: 2023 | D2: 2024 | E2: 2025 | F2: 2026 | G2: 2027
A3: 1 | B3: Current Ratio | C3: ='Balance sheet'!G24/'Balance sheet'!G46 -> 6.6184737 | D3: ='Balance sheet'!H24/'Balance sheet'!H46 -> 18.228282 | E3: ='Balance sheet'!I24/'Balance sheet'!I46 -> 10.390287 | F3: ='Balance sheet'!J24/'Balance sheet'!J46 -> 30.589837 | G3: ='Balance sheet'!K24/'Balance sheet'!K46 -> 13.968626
A4: 2 | B4: Quick Ratio | C4: =('Balance sheet'!G24-'Balance sheet'!G16)/'Balance sheet'!G46 -> 5.6193664 | D4: =('Balance sheet'!H24-'Balance sheet'!H16)/'Balance sheet'!H46 -> 18.041907 | E4: =('Balance sheet'!I24-'Balance sheet'!I16)/'Balance sheet'!I46 -> 10.05863 | F4: =('Balance sheet'!J24-'Balance sheet'!J16)/'Balance sheet'!J46 -> 29.667867 | G4: =('Balance sheet'!K24-'Balance sheet'!K16)/'Balance sheet'!K46 -> 13.597631
A5: 3 | B5: ROE | C5: ='Model- Income statement'!G40/'Balance sheet'!G31 -> 0.48800646 | D5: ='Model- Income statement'!H40/'Balance sheet'!H31 -> 0.52820851 | E5: ='Model- Income statement'!I40/'Balance sheet'!I31 -> 0.33740721 | F5: ='Model- Income statement'!J40/'Balance sheet'!J31 -> 0.30367775 | G5: ='Model- Income statement'!K40/'Balance sheet'!K31 -> 0.2681825
A6: 4 | B6: ROCE | C6: ='Model- Income statement'!G40/('Balance sheet'!G31+'Balance sheet'!G38) -> 0.47610486 | D6: ='Model- Income statement'!H40/('Balance sheet'!H31+'Balance sheet'!H38) -> 0.52027549 | E6: ='Model- Income statement'!I40/('Balance sheet'!I31+'Balance sheet'!I38) -> 0.33349829 | F6: ='Model- Income statement'!J40/('Balance sheet'!J31+'Balance sheet'!J38) -> 0.30084909 | G6: ='Model- Income statement'!K40/('Balance sheet'!K31+'Balance sheet'!K38) -> 0.26608479
A7: 5 | B7: EPS | C7: =+'Model- Income statement'!G40/Input!I135 -> 55.939936 | D7: =+'Model- Income statement'!H40/Input!J135 -> 102.84163 | E7: =+'Model- Income statement'!I40/Input!K135 -> 89.244189 | F7: =+'Model- Income statement'!J40/Input!L135 -> 105.04515 | G7: =+'Model- Income statement'!K40/Input!M135 -> 117.1066
A8: 6 | B8: DPS | C8: =C7*Input!$G$114 -> 12.586486 | D8: =D7*Input!$G$114 -> 23.139367 | E8: =E7*Input!$G$114 -> 20.079943 | F8: =F7*Input!$G$114 -> 23.63516 | G8: =G7*Input!$G$114 -> 26.348985
A9: 7 | B9: BVPS | C9: =(('Balance sheet'!G25-'Balance sheet'!G46-'Balance sheet'!G35))/(Input!I135) -> 121.67059 | D9: =(('Balance sheet'!H25-'Balance sheet'!H46-'Balance sheet'!H35))/(Input!J135) -> 197.34009 | E9: =(('Balance sheet'!I25-'Balance sheet'!I46-'Balance sheet'!I35))/(Input!K135) -> 291.46108 | F9: =(('Balance sheet'!J25-'Balance sheet'!J46-'Balance sheet'!J35))/(Input!L135) -> 352.34074 | G9: =(('Balance sheet'!K25-'Balance sheet'!K46-'Balance sheet'!K35))/(Input!M135) -> 474.86614
A10: 8 | B10: NP Margin | C10: ='Model- Income statement'!G40/'Model- Income statement'!G17 -> 0.42162194 | D10: ='Model- Income statement'!H40/'Model- Income statement'!H17 -> 0.68346904 | E10: ='Model- Income statement'!I40/'Model- Income statement'!I17 -> 0.51853633 | F10: ='Model- Income statement'!J40/'Model- Income statement'!J17 -> 0.53072408 | G10: ='Model- Income statement'!K40/'Model- Income statement'!K17 -> 0.51000234
A11: 9 | B11: Debt to Equity | C11: =('Balance sheet'!G35+'Balance sheet'!G41)/Input!I116 -> 0.091255041 | D11: =('Balance sheet'!H35+'Balance sheet'!H41)/Input!J116 -> 0.036839898 | E11: =('Balance sheet'!I35+'Balance sheet'!I41)/Input!K116 -> 0.067392921 | F11: =('Balance sheet'!J35+'Balance sheet'!J41)/Input!L116 -> 0.023774214 | G11: =('Balance sheet'!K35+'Balance sheet'!K41)/Input!M116 -> 0.050535196
A12: 10 | B12: Inventory Turnover Ratio | C12: ='Model- Income statement'!G27/AVERAGE('Balance sheet'!F16:G16) -> 2.0917374 | D12: ='Model- Income statement'!H27/AVERAGE('Balance sheet'!G16:H16) -> 1.0124557 | E12: ='Model- Income statement'!I27/AVERAGE('Balance sheet'!H16:I16) -> 7.3393859 | F12: ='Model- Income statement'!J27/AVERAGE('Balance sheet'!I16:J16) -> 4.5767803 | G12: ='Model- Income statement'!K27/AVERAGE('Balance sheet'!J16:K16) -> 4.9266162
A13: 11 | B13: Debtors Turnover Ratio | C13: ='Model- Income statement'!G17/AVERAGE('Balance sheet'!F19:G19) -> 9.1771503 | D13: ='Model- Income statement'!H17/AVERAGE('Balance sheet'!G19:H19) -> 9.1771503 | E13: ='Model- Income statement'!I17/AVERAGE('Balance sheet'!H19:I19) -> 9.1771503 | F13: ='Model- Income statement'!J17/AVERAGE('Balance sheet'!I19:J19) -> 9.1771503 | G13: ='Model- Income statement'!K17/AVERAGE('Balance sheet'!J19:K19) -> 9.1771503
A14: 12 | B14: Creditors Turnover Ratio | C14: ='Model- Income statement'!G27/AVERAGE('Balance sheet'!F42:G42) -> 15.42081 | D14: ='Model- Income statement'!H27/AVERAGE('Balance sheet'!G42:H42) -> 15.42081 | E14: ='Model- Income statement'!I27/AVERAGE('Balance sheet'!H42:I42) -> 15.42081 | F14: ='Model- Income statement'!J27/AVERAGE('Balance sheet'!I42:J42) -> 15.42081 | G14: ='Model- Income statement'!K27/AVERAGE('Balance sheet'!J42:K42) -> 15.42081
A15: 13 | B15: Sales CAGR | C15: =('Model- Income statement'!G25/'Model- Income statement'!F25)-1 -> 0.1131151 | D15: =('Model- Income statement'!H25/'Model- Income statement'!G25)-1 -> 0.12894281 | E15: =('Model- Income statement'!I25/'Model- Income statement'!H25)-1 -> 0.13868856 | F15: =('Model- Income statement'!J25/'Model- Income statement'!I25)-1 -> 0.1487323 | G15: =('Model- Income statement'!K25/'Model- Income statement'!J25)-1 -> 0.1589258
A16: 14 | B16: Net Profit CAGR | C16: =('Model- Income statement'!G40/'Model- Income statement'!F40)-1 -> 1.6337321 | D16: =('Model- Income statement'!H40/'Model- Income statement'!G40)-1 -> 0.83245587 | E16: =('Model- Income statement'!I40/'Model- Income statement'!H40)-1 -> -0.13504618 | F16: =('Model- Income statement'!J40/'Model- Income statement'!I40)-1 -> 0.17705315 | G16: =('Model- Income statement'!K40/'Model- Income statement'!J40)-1 -> 0.11482153
A17: 15 | B17: EV/Sales | C17: =Input!I144 -> 7.1740842 | D17: =Input!J144 -> 11.276752 | E17: =Input!K144 -> 8.0906897 | F17: =Input!L144 -> 8.1780449 | G17: =Input!M144 -> 7.5473694
A18: 16 | B18: EV/EBIT | C18: =Input!I145 -> 12.598392 | D18: =Input!J145 -> 12.22487 | E18: =Input!K145 -> 11.539394 | F18: =Input!L145 -> 11.386575 | G18: =Input!M145 -> 10.924951
A19: 17 | B19: MPS | C19: =C7*Input!$G$141 -> 997.67013 | D19: =D7*Input!$G$141 -> 1834.1462 | E19: =E7*Input!$G$141 -> 1591.6404 | F19: =F7*Input!$G$141 -> 1873.4454 | G19: =G7*Input!$G$141 -> 2088.5572
A20: 18 | B20: P/E | C20: =C19/C7 -> 17.834667 | D20: =D19/D7 -> 17.834667 | E20: =E19/E7 -> 17.834667 | F20: =F19/F7 -> 17.834667 | G20: =G19/G7 -> 17.834667
A21: 19 | B21: P/B | C21: =C19/C9 -> 8.1997642 | D21: =D19/D9 -> 9.2943419 | E21: =E19/E9 -> 5.460902 | F21: =F19/F9 -> 5.3171409 | G21: =G19/G9 -> 4.398202
A22: 20 | B22: P/S | C22: =Input!I138/'Model- Income statement'!G13 -> 5.312973 | D22: =Input!J138/'Model- Income statement'!H13 -> 8.8392275 | E22: =Input!K138/'Model- Income statement'!I13 -> 6.7283584 | F22: =Input!L138/'Model- Income statement'!J13 -> 6.9508526 | G22: =Input!M138/'Model- Income statement'!K13 -> 6.7293504

Sheet Beta & Rm
B2: KPR Mills Ltd | G2: Nifty - 50
B3: Date | C3: Adj Close | D3: Ri | G3: Date | H3: Close | I3: Rm
B4: 44287 | C4: 210.91299 | G4: 44287 | H4: 14867.35
B5: 44291 | C5: 208.61731 | D5: =C5/C4-1 -> -0.010884507 | G5: 44291 | H5: 14637.8 | I5: =H5/H4-1 -> -0.015439861 | K5: Beta | L5: =SLOPE(D4:D250,I4:I250) -> 0.9819997
B6: 44292 | C6: 212.79126 | D6: =C6/C5-1 -> 0.020007688 | G6: 44292 | H6: 14683.5 | I6: =H6/H5-1 -> 0.0031220672 | K6: Rm | L6: =D250/D5-1 -> 1.6678483
B7: 44293 | C7: 212.75153 | D7: =C7/C6-1 -> -0.00018672759 | G7: 44293 | H7: 14819.05 | I7: =H7/H6-1 -> 0.009231437 | K7: Rf | L7: 0.06
B8: 44294 | C8: 213.90433 | D8: =C8/C7-1 -> 0.0054185322 | G8: 44294 | H8: 14873.8 | I8: =H8/H7-1 -> 0.0036945689
B9: 44295 | C9: 218.25714 | D9: =C9/C8-1 -> 0.02034935 | G9: 44295 | H9: 14834.85 | I9: =H9/H8-1 -> -0.0026187119 | L9: =STDEV(D5:D250)*SQRT(247) -> 0.47758657
B10: 44298 | C10: 214.05339 | D10: =C10/C9-1 -> -0.019260538 | G10: 44298 | H10: 14310.8 | I10: =H10/H9-1 -> -0.035325589
B11: 44299 | C11: 244.53308 | D11: =C11/C10-1 -> 0.14239293 | G11: 44299 | H11: 14504.8 | I11: =H11/H10-1 -> 0.013556196
B12: 44301 | C12: 244.19518 | D12: =C12/C11-1 -> -0.0013818417 | G12: 44301 | H12: 14581.45 | I12: =H12/H11-1 -> 0.0052844845
B13: 44302 | C13: 236.01625 | D13: =C13/C12-1 -> -0.033493389 | G13: 44302 | H13: 14617.85 | I13: =H13/H12-1 -> 0.0024962822
B14: 44305 | C14: 246.03371 | D14: =C14/C13-1 -> 0.042443925 | G14: 44305 | H14: 14359.45 | I14: =H14/H13-1 -> -0.017676979
B15: 44306 | C15: 242.56535 | D15: =C15/C14-1 -> -0.014097068 | G15: 44306 | H15: 14296.4 | I15: =H15/H14-1 -> -0.004390823
B16: 44308 | C16: 235.74793 | D16: =C16/C15-1 -> -0.028105531 | G16: 44308 | H16: 14406.15 | I16: =H16/H15-1 -> 0.0076767576
B17: 44309 | C17: 242.07838 | D17: =C17/C16-1 -> 0.026852661 | G17: 44309 | H17: 14341.35 | I17: =H17/H16-1 -> -0.0044981331
B18: 44312 | C18: 251.7679 | D18: =C18/C17-1 -> 0.040026354 | G18: 44312 | H18: 14485 | I18: =H18/H17-1 -> 0.010016518
B19: 44313 | C19: 259.55924 | D19: =C19/C18-1 -> 0.030946503 | G19: 44313 | H19: 14653.05 | I19: =H19/H18-1 -> 0.011601643
B20: 44314 | C20: 267.56921 | D20: =C20/C19-1 -> 0.030859927 | G20: 44314 | H20: 14864.55 | I20: =H20/H19-1 -> 0.014433855
B21: 44315 | C21: 270.68976 | D21: =C21/C20-1 -> 0.011662567 | G21: 44315 | H21: 14894.9 | I21: =H21/H20-1 -> 0.00204181
... B250: 44650 | C250: 612.98328 | D250: =C250/C249-1 -> -0.029038214 | G250: 44650 | H250: 17498.25 | I250: =H250/H249-1 -> 0.0099824656

Sheet Scenario Summary DDM
B2: Scenario Summary
D3: Current Values: | E3: Original | F3: Optimistic | G3: Pessimistic
E4: Created by Ananya Chengta on 22-03-2023 Modified by BHARATHI KYATHI GANAPATHIRAJU on 22-03-2023 | F4: Created by BHARATHI KYATHI GANAPATHIRAJU on 22-03-2023 | G4: Created by BHARATHI KYATHI GANAPATHIRAJU on 22-03-2023
B5: Changing Cells:
C6: Stable_Growth_Rate | D6: 0.14 | E6: 0.14 | F6: 0.17 | G6: 0.1
B7: Result Cells:
C8: Value_Per_Share | D8: 430.12929 | E8: 430.12929 | F8: 2496.6698 | G8: 251.48787
B9: Notes: Current Values column represents values of changing cells at
B10: time Scenario Summary Report was created. Changing cells for each
B11: scenario are highlighted in gray.

Sheet Valuation- DDM
C2: Stage- 1 | I2: Transition Phase | M2: Stable Phase
B3: Year | C3: 2022 | D3: 2023 | E3: 2024 | F3: 2025 | G3: 2026 | H3: 2027 | I3: =H3+1 -> 2028 | J3: =I3+1 -> 2029 | K3: =J3+1 -> 2030 | L3: =K3+1 -> 2031 | M3: =L3+1 -> 2032
C4: 0 | D4: 1 | E4: 2 | F4: 3 | G4: 4 | H4: 5 | I4: 6 | J4: 7 | K4: 8 | L4: 9 | M4: 10
B5: Dividend | C5: =Input!F113 -> 516 | D5: =Input!I113 -> 43306.457 | E5: =Input!J113 -> 79357.171 | F5: =Input!K113 -> 68640.288 | G5: =Input!L113 -> 80793.267 | H5: =Input!M113 -> 90070.074 | I5: =H5*(1+I6) -> 100865.62 | J5: =I5*(1+J6) -> 113463.02 | K5: =J5*(1+K6) -> 128205.12 | L5: =K5*(1+L6) -> 145508.23 | M5: =L5*(1+M6) -> 165879.39
B6: Dividend Growth | H6: =H5/G5-1 -> 0.11482153 | I6: =H6+$C$17 -> 0.11985722 | J6: =I6+$C$17 -> 0.12489292 | K6: =J6+$C$17 -> 0.12992861 | L6: =K6+$C$17 -> 0.13496431 | M6: ='Assumptions '!C42 -> 0.14
B7: Terminal value | L7: =L5*(1+C16)/(C18-C16) -> 110666.93
B8: Total DDM | D8: =D5+D7 -> 43306.457 | E8: =E5+E7 -> 79357.171 | F8: =F5+F7 -> 68640.288 | G8: =G5+G7 -> 80793.267 | H8: =H5+H7 -> 90070.074 | I8: =I5+I7 -> 100865.62 | J8: =J5+J7 -> 113463.02 | K8: =K5+K7 -> 128205.12 | L8: =L5+L7 -> 256175.16
B9: Value of Equity | C9: =NPV(C18,D8:L8) -> 34433.144
B10: Total No of shares | C10: =Input!F135 -> 3440.7108
B11: Value per share | C11: =C9/C10 -> 10.007567
B14: Working
B15: H (High Growth) | C15: =H6 -> 0.11482153
B16: g (Stable Growth) | C16: 0.14
B17: Growth Factor | C17: =(M6-H6)/5 -> 0.0050356939
B18: Ke | C18: =C19+C20*(C21-C19) -> 1.6389065
B19: Rf | C19: ='Beta & Rm'!L7 -> 0.06
B20: Beta | C20: ='Beta & Rm'!L5 -> 0.9819997
B21: Rm | C21: ='Beta & Rm'!L6 -> 1.6678483

Sheet Valuation- FCFF 
C2: Stage- 1 | I2: Transition Phase | M2: Stable Phase
B3: Year | C3: 2022 | D3: 2023 | E3: 2024 | F3: 2025 | G3: 2026 | H3: 2027 | I3: =H3+1 -> 2028 | J3: =I3+1 -> 2029 | K3: =J3+1 -> 2030 | L3: =K3+1 -> 2031 | M3: =L3+1 -> 2032
C4: 0 | D4: 1 | E4: 2 | F4: 3 | G4: 4 | H4: 5 | I4: 6 | J4: 7 | K4: 8 | L4: 9 | M4: 10
B5: PAT | C5: ='Model- Income statement'!F40 -> 73080 | D5: ='Model- Income statement'!G40 -> 192473.14 | E5: ='Model- Income statement'!H40 -> 352698.54 | F5: ='Model- Income statement'!I40 -> 305067.95 | G5: ='Model- Income statement'!J40 -> 359081.19 | H5: ='Model- Income statement'!K40 -> 400311.44
B6: (+): Non Cash Charges | C6: ='Model- Income statement'!F32 -> 7565 | D6: ='Model- Income statement'!G32 -> 7012.0516 | E6: ='Model- Income statement'!H32 -> 6499.5199 | F6: ='Model- Income statement'!I32 -> 6024.4507 | G6: ='Model- Income statement'!J32 -> 5584.1056 | H6: ='Model- Income statement'!K32 -> 5175.9467
B7: Interest | C7: ='Model- Income statement'!F31 -> 1339 | D7: ='Model- Income statement'!G31 -> 1146.0181 | E7: ='Model- Income statement'!H31 -> 1213.9158 | F7: ='Model- Income statement'!I31 -> 1300.2671 | G7: ='Model- Income statement'!J31 -> 1408.8186 | H7: ='Model- Income statement'!K31 -> 1544.3712
B8: (+): Interest*(1 - Tax) | C8: =C7*(1-Input!$G$54) -> 982.43273 | D8: =D7*(1-Input!$G$54) -> 840.84068 | E8: =E7*(1-Input!$G$54) -> 890.65769 | F8: =F7*(1-Input!$G$54) -> 954.01414 | G8: =G7*(1-Input!$G$54) -> 1033.659 | H8: =H7*(1-Input!$G$54) -> 1133.1149
B9: (-) Capex | C9: =Input!F68 -> 13552 | D9: =Input!I68 -> 13496.526 | E9: =Input!J68 -> 15256.674 | F9: =Input!K68 -> 17393.719 | G9: =Input!L68 -> 20003.175 | H9: =Input!M68 -> 23206.033
B10: Working Capital | C10: ='Balance sheet'!F24-'Balance sheet'!F46-'Balance sheet'!F20 -> 109110 | D10: ='Balance sheet'!G24-'Balance sheet'!G46-'Balance sheet'!G20 -> 123283.01 | E10: ='Balance sheet'!H24-'Balance sheet'!H46-'Balance sheet'!H20 -> 110698.39 | F10: ='Balance sheet'!I24-'Balance sheet'!I46-'Balance sheet'!I20 -> 125692.33 | G10: ='Balance sheet'!J24-'Balance sheet'!J46-'Balance sheet'!J20 -> 158518.2 | H10: ='Balance sheet'!K24-'Balance sheet'!K46-'Balance sheet'!K20 -> 160669.13
B11: (-) Change in Working Capital | D11: =D10-C10 -> 14173.014 | E11: =E10-D10 -> -12584.623 | F11: =F10-E10 -> 14993.934 | G11: =G10-F10 -> 32825.878 | H11: =H10-G10 -> 2150.9235
B12: FCFF | D12: =D5+D6+D8-D9-D11 -> 172656.49 | E12: =E5+E6+E8-E9-E11 -> 357416.66 | F12: =F5+F6+F8-F9-F11 -> 279658.76 | G12: =G5+G6+G8-G9-G11 -> 312869.9 | H12: =H5+H6+H8-H9-H11 -> 381263.54 | I12: =H12*(1-I14) -> 303912.52 | J12: =I12*(1-J14) -> 247032.08 | K12: =J12*(1-K14) -> 204680.81 | L12: =K12*(1-L14) -> 172807.88 | M12: =L12*(1-M14) -> 148614.78
B13: FCFF Growth Rate Factor | C13: =(H14-M14)/5 -> 0.015720183
B14: FCFF Growth Rate | H14: =H12/G12-1 -> 0.21860091 | I14: =H14-$C$13 -> 0.20288073 | J14: =I14-$C$13 -> 0.18716055 | K14: =J14-$C$13 -> 0.17144037 | L14: =K14-$C$13 -> 0.15572018 | M14: ='Assumptions '!$C$42 -> 0.14
B15: Terminal Value | L15: =M12/(H35-M14) -> 104426.17
B16: Total | D16: =D12+D15 -> 172656.49 | E16: =E12+E15 -> 357416.66 | F16: =F12+F15 -> 279658.76 | G16: =G12+G15 -> 312869.9 | H16: =H12+H15 -> 381263.54 | I16: =I12+I15 -> 303912.52 | J16: =J12+J15 -> 247032.08 | K16: =K12+K15 -> 204680.81 | L16: =L12+L15 -> 277234.05
B17: Value of Firm | C17: =NPV(C35,D16:L16) -> 167688.94
B18: Less: Debt | C18: ='Balance sheet'!F35+'Balance sheet'!F41 -> 41785
B19: Add: Cash and Cash Equivalents | C19: =Case!F63 -> 9561
B20: Value of Equity | C20: =C17-C18+C19 -> 135464.94
B21: No of shares | C21: =Input!F110 -> 3440.7108
B22: Value per Share | C22: =C20/C21 -> 39.371209
B26: WACC Computation
B27: Debt | C27: ='Balance sheet'!F35+'Balance sheet'!F41 -> 41785 | D27: ='Balance sheet'!G35+'Balance sheet'!G41 -> 35991.623 | E27: ='Balance sheet'!H35+'Balance sheet'!H41 -> 24598.956 | F27: ='Balance sheet'!I35+'Balance sheet'!I41 -> 60933.554 | G27: ='Balance sheet'!J35+'Balance sheet'!J41 -> 28111.618 | H27: ='Balance sheet'!K35+'Balance sheet'!K41 -> 75433.023
B28: Equity | C28: ='Balance sheet'!F31 -> 263218 | D28: ='Balance sheet'!G31 -> 394406.95 | E28: ='Balance sheet'!H31 -> 667725.96 | F28: ='Balance sheet'!I31 -> 904153.62 | G28: ='Balance sheet'!J31 -> 1182441.5 | H28: ='Balance sheet'!K31 -> 1492682.9
B29: Total | C29: =SUM(C27:C28) -> 305003 | D29: =SUM(D27:D28) -> 430398.58 | E29: =SUM(E27:E28) -> 692324.92 | F29: =SUM(F27:F28) -> 965087.17 | G29: =SUM(G27:G28) -> 1210553.2 | H29: =SUM(H27:H28) -> 1568115.9
B30: Equity Weight | C30: =C28/C29 -> 0.86300135 | D30: =D28/D29 -> 0.91637606 | E30: =E28/E29 -> 0.96446906 | F30: =F28/F29 -> 0.93686212 | G30: =G28/G29 -> 0.97677787 | H30: =H28/H29 -> 0.95189576
B31: Debt Weight | C31: =1-C30 -> 0.13699865 | D31: =1-D30 -> 0.083623935 | E31: =1-E30 -> 0.035530941 | F31: =1-F30 -> 0.063137876 | G31: =1-G30 -> 0.023222126 | H31: =1-H30 -> 0.048104239
B32: Ke | C32: ='Beta & Rm'!$L$7+'Beta & Rm'!$L$5*('Beta & Rm'!$L$6-'Beta & Rm'!$L$7) -> 1.6389065 | D32: ='Beta & Rm'!$L$7+'Beta & Rm'!$L$5*('Beta & Rm'!$L$6-'Beta & Rm'!$L$7) -> 1.6389065 | E32: ='Beta & Rm'!$L$7+'Beta & Rm'!$L$5*('Beta & Rm'!$L$6-'Beta & Rm'!$L$7) -> 1.6389065 | F32: ='Beta & Rm'!$L$7+'Beta & Rm'!$L$5*('Beta & Rm'!$L$6-'Beta & Rm'!$L$7) -> 1.6389065 | G32: ='Beta & Rm'!$L$7+'Beta & Rm'!$L$5*('Beta & Rm'!$L$6-'Beta & Rm'!$L$7) -> 1.6389065 | H32: ='Beta & Rm'!$L$7+'Beta & Rm'!$L$5*('Beta & Rm'!$L$6-'Beta & Rm'!$L$7) -> 1.6389065
B33: Pre-Tax Kd | C33: =Input!$G$49 -> 0.0875 | D33: =Input!$G$49 -> 0.0875 | E33: =Input!$G$49 -> 0.0875 | F33: =Input!$G$49 -> 0.0875 | G33: =Input!$G$49 -> 0.0875 | H33: =Input!$G$49 -> 0.0875
B34: Post Tax Kd | C34: =C33*(1-Input!$G$54) -> 0.064199301 | D34: =D33*(1-Input!$G$54) -> 0.064199301 | E34: =E33*(1-Input!$G$54) -> 0.064199301 | F34: =F33*(1-Input!$G$54) -> 0.064199301 | G34: =G33*(1-Input!$G$54) -> 0.064199301 | H34: =H33*(1-Input!$G$54) -> 0.064199301
B35: WACC | C35: =C31*C34+C32*C30 -> 1.4231738 | D35: =D31*D34+D32*D30 -> 1.5072233 | E35: =E31*E34+E32*E30 -> 1.5829557 | F35: =F31*F34+F32*F30 -> 1.5394829 | G35: =G31*G34+G32*G30 -> 1.6023385 | H35: =H31*H34+H32*H30 -> 1.5631564
B40: Data Table
D41: Number of shares
C42: =C22 -> 39.371209 | D42: 3440.71 | E42: 3590.71 | F42: 3740.71 | G42: 3890.71 | H42: 4040.71
B43: Stable growth Rate | C43: 0.14 | D43: 39.371218 | E43: 37.726506 | F43: 36.213698 | G43: 34.817538 | H43: 33.525035
C44: 0.12 | D44: 39.378546 | E44: 37.733528 | F44: 36.220438 | G44: 34.824018 | H44: 33.531274
C45: 0.1 | D45: 39.385968 | E45: 37.74064 | F45: 36.227265 | G45: 34.830582 | H45: 33.537595
C46: 0.08 | D46: 39.393487 | E46: 37.747845 | F46: 36.234181 | G46: 34.837231 | H46: 33.543997
C47: 0.06 | D47: 39.401103 | E47: 37.755143 | F47: 36.241187 | G47: 34.843967 | H47: 33.550482

Sheet Relative Valuation
B2: Computation of Multiples
B3: Sr No. | C3: Comparable Companies | D3: EV/Sales | E3: EV/Total Assets | F3: EV/EBITDA
B4: 1 | C4: Page Industry | D4: 12.86 | E4: 22.73 | F4: 59.39
B5: 2 | C5: Trident Ltd | D5: 4.08 | E5: 4.41 | F5: 18.48
B6: 3 | C6: Swan Energy | D6: 12.75 | E6: 3.24 | F6: 115.99
B7: 4 | C7: Raymond | D7: 1.69 | E7: 1.22 | F7: 8.51
B8: 5 | C8: Welspun India | D8: 1.5 | E8: 1.64 | F8: 8.43
C9: Average | D9: =AVERAGE(D4:D8) -> 6.576 | E9: =AVERAGE(E4:E8) -> 6.648 | F9: =AVERAGE(F4:F8) -> 42.16
B12: Computation of Enterprise Value of KPR Mills by EV Ratios
C13: KPR Mills Ltd | D13: Multiples | F13: EV
B14: Sales | C14: =Case!F18 -> 407367 | D14: =D9 -> 6.576 | E14: =C14*D14 -> 2678845.4 | F14: =AVERAGE(E14:E16) -> 3662155.2
B15: Total Assets | C15: =Case!F68 -> 335890 | D15: =E9 -> 6.648 | E15: =C15*D15 -> 2232996.7
B16: EBITDA | C16: =Case!F36+Case!F34 -> 144085 | D16: =F9 -> 42.16 | E16: =C16*D16 -> 6074623.6
B19: Enterprise Value = Market Value of Debt + Market Value of Equity Shares + Market Value of Preference Shares - Closing Cash
B22: Particulars | C22: Amt (Rs)
B23: Market Value of Debt | C23: =('Balance sheet'!F41+'Balance sheet'!F35) -> 41785
B24: Cash and Cash Equvivalent | C24: ='Balance sheet'!F20 -> 9561
B25: Equity Value | C25: =F14-C23+C24 -> 3629931.2
B26: No of Shares | C26: =Input!F110 -> 3440.7108
B27: Equity Value Per Share (EV Based) | C27: =C25/C26 -> 1054.9946

Sheet Buy & Sell Decision
B3: Buy/Sell Decision
B4: Valuation Method | C4: Value per Share | D4: Market Price | E4: Status | F4: Decision
B5: DDM | D5: =Input!$F$137 -> 615.25 | E5: =IF(D5<C5,"Undervalued","Overvalued") -> Overvalued | F5: =IF(D5<C5,"Buy","Sell") -> Sell
B6: (i) Original | C6: ='Scenario Summary DDM'!E8 -> 430.12929 | D6: =Input!$F$137 -> 615.25 | E6: =IF(D6<C6,"Undervalued","Overvalued") -> Overvalued | F6: =IF(D6<C6,"Buy","Sell") -> Sell
B7: (ii) Optimistic | C7: ='Scenario Summary DDM'!F8 -> 2496.6698 | D7: =Input!$F$137 -> 615.25 | E7: =IF(D7<C7,"Undervalued","Overvalued") -> Undervalued | F7: =IF(D7<C7,"Buy","Sell") -> Buy
B8: (iii) Pessimistic | C8: ='Scenario Summary DDM'!G8 -> 251.48787 | D8: =Input!$F$137 -> 615.25 | E8: =IF(D8<C8,"Undervalued","Overvalued") -> Overvalued | F8: =IF(D8<C8,"Buy","Sell") -> Sell
B9: FCFF | C9: ='Valuation- FCFF '!C22 -> 39.371209 | D9: =Input!$F$137 -> 615.25 | E9: =IF(D9<C9,"Undervalued","Overvalued") -> Overvalued | F9: =IF(D9<C9,"Buy","Sell") -> Sell
B10: Relative | C10: ='Relative Valuation'!C27 -> 1054.9946 | D10: =Input!$F$137 -> 615.25 | E10: =IF(D10<C10,"Undervalued","Overvalued") -> Undervalued | F10: =IF(D10<C10,"Buy","Sell") -> Buy
